{"datas":{"kzkccx":{"totalSize":113,"pageSize":999,"rows":[{"PYFADM":"61ff62ed9a3a480eaf7ca0bbbe3e8bd0","XS":"32.0","KCXZDM_DISPLAY":"必修","WID":"C1CCC44EC91B05B0E0530D13AC0A4A70","XNXQ_DISPLAY":"2020-2021学年第一学期","KKDWDM_DISPLAY":"军事教研室","BZ":null,"XXKC":null,"SFZGKC":null,"XF":"2.0","JHXNDM":null,"KSLXDM_DISPLAY":"考试","KCXZDM":"001","XDXQ":"1","SFZGKC_DISPLAY":"","XDXNXQ":null,"KKDWDM":"2121","KSLXDM":"1","JHXQDM":null,"KZH":"3a0401dbd12547e38997f59d2ad4110c","KZM":"通识教育基础课","XNXQ":"2020-2021-1","CXXQ":null,"KCM":"军事理论","PX":null,"KCH":"AM006001"},{"PYFADM":"61ff62ed9a3a480eaf7ca0bbbe3e8bd0","XS":"2.0","KCXZDM_DISPLAY":"必修","WID":"C1CCC44EC91C05B0E0530D13AC0A4A70","XNXQ_DISPLAY":"2020-2021学年第一学期","KKDWDM_DISPLAY":"军事教研室","BZ":null,"XXKC":null,"SFZGKC":null,"XF":"1.0","JHXNDM":null,"KSLXDM_DISPLAY":"考查","KCXZDM":"001","XDXQ":"1","SFZGKC_DISPLAY":"","XDXNXQ":null,"KKDWDM":"2121","KSLXDM":"2","JHXQDM":null,"KZH":"3a0401dbd12547e38997f59d2ad4110c","KZM":"通识教育基础课","XNXQ":"2020-2021-1","CXXQ":null,"KCM":"军事训练","PX":null,"KCH":"AM006002"},{"PYFADM":"61ff62ed9a3a480eaf7ca0bbbe3e8bd0","XS":"64.0","KCXZDM_DISPLAY":"必修","WID":"C1CCC44EC91A05B0E0530D13AC0A4A70","XNXQ_DISPLAY":"2020-2021学年第一学期","KKDWDM_DISPLAY":"计算机科学与技术学院","BZ":null,"XXKC":null,"SFZGKC":null,"XF":"4.0","JHXNDM":null,"KSLXDM_DISPLAY":"考试","KCXZDM":"001","XDXQ":"1","SFZGKC_DISPLAY":"","XDXNXQ":null,"KKDWDM":"1103","KSLXDM":"1","JHXQDM":null,"KZH":"2018060003_ggkz","KZM":"大类基础课","XNXQ":"2020-2021-1","CXXQ":null,"KCM":"计算机导论与程序设计","PX":null,"KCH":"CS006001"},{"PYFADM":"61ff62ed9a3a480eaf7ca0bbbe3e8bd0","XS":"32.0","KCXZDM_DISPLAY":"必修","WID":"D57C8321A3E96A7CE0530D13AC0ADBDC","XNXQ_DISPLAY":"2021-2022学年第一学期, 2021-2022学年第二学期","KKDWDM_DISPLAY":"经济与管理学院","BZ":null,"XXKC":null,"SFZGKC":"0","XF":"2.0","JHXNDM":null,"KSLXDM_DISPLAY":"考查","KCXZDM":"001","XDXQ":"3,4","SFZGKC_DISPLAY":"否","XDXNXQ":null,"KKDWDM":"1106","KSLXDM":"2","JHXQDM":null,"KZH":"0f1b4df14f8b4beb83962542aa074756","KZM":"2021试点班-素质能力拓展","XNXQ":"2021-2022-1,2021-2022-2","CXXQ":null,"KCM":"创业基础","PX":null,"KCH":"EM001001"},{"PYFADM":"61ff62ed9a3a480eaf7ca0bbbe3e8bd0","XS":"32.0","KCXZDM_DISPLAY":"必修","WID":"C1CCC44EC91D05B0E0530D13AC0A4A70","XNXQ_DISPLAY":"2020-2021学年第一学期","KKDWDM_DISPLAY":"外国语学院","BZ":null,"XXKC":null,"SFZGKC":null,"XF":"2.0","JHXNDM":null,"KSLXDM_DISPLAY":"考试","KCXZDM":"001","XDXQ":"1","SFZGKC_DISPLAY":"","XDXNXQ":null,"KKDWDM":"1109","KSLXDM":"1","JHXQDM":null,"KZH":"3a0401dbd12547e38997f59d2ad4110c","KZM":"通识教育基础课","XNXQ":"2020-2021-1","CXXQ":null,"KCM":"大学英语(Ⅰ)","PX":null,"KCH":"FL006001"},{"PYFADM":"61ff62ed9a3a480eaf7ca0bbbe3e8bd0","XS":"32.0","KCXZDM_DISPLAY":"必修","WID":"C1CCC44EC92405B0E0530D13AC0A4A70","XNXQ_DISPLAY":"2020-2021学年第二学期","KKDWDM_DISPLAY":"外国语学院","BZ":null,"XXKC":null,"SFZGKC":null,"XF":"2.0","JHXNDM":null,"KSLXDM_DISPLAY":"考试","KCXZDM":"001","XDXQ":"2","SFZGKC_DISPLAY":"","XDXNXQ":null,"KKDWDM":"1109","KSLXDM":"1","JHXQDM":null,"KZH":"3a0401dbd12547e38997f59d2ad4110c","KZM":"通识教育基础课","XNXQ":"2020-2021-2","CXXQ":null,"KCM":"大学英语(Ⅱ)","PX":null,"KCH":"FL006002"},{"PYFADM":"61ff62ed9a3a480eaf7ca0bbbe3e8bd0","XS":"32.0","KCXZDM_DISPLAY":"必修","WID":"C1CCC44EC91E05B0E0530D13AC0A4A70","XNXQ_DISPLAY":"2020-2021学年第一学期, 2021-2022学年第一学期","KKDWDM_DISPLAY":"外国语学院","BZ":null,"XXKC":null,"SFZGKC":"0","XF":"2.0","JHXNDM":null,"KSLXDM_DISPLAY":"考试","KCXZDM":"001","XDXQ":"1,3","SFZGKC_DISPLAY":"否","XDXNXQ":null,"KKDWDM":"1109","KSLXDM":"1","JHXQDM":null,"KZH":"3a0401dbd12547e38997f59d2ad4110c","KZM":"通识教育基础课","XNXQ":"2020-2021-1,2021-2022-1","CXXQ":null,"KCM":"大学英语中级(I)","PX":null,"KCH":"FL006003"},{"PYFADM":"61ff62ed9a3a480eaf7ca0bbbe3e8bd0","XS":"32.0","KCXZDM_DISPLAY":"必修","WID":"C1CCC44EC92A05B0E0530D13AC0A4A70","XNXQ_DISPLAY":"2020-2021学年第二学期, 2021-2022学年第二学期","KKDWDM_DISPLAY":"外国语学院","BZ":null,"XXKC":null,"SFZGKC":"0","XF":"2.0","JHXNDM":null,"KSLXDM_DISPLAY":"考试","KCXZDM":"001","XDXQ":"2,4","SFZGKC_DISPLAY":"否","XDXNXQ":null,"KKDWDM":"1109","KSLXDM":"1","JHXQDM":null,"KZH":"3a0401dbd12547e38997f59d2ad4110c","KZM":"通识教育基础课","XNXQ":"2020-2021-2,2021-2022-2","CXXQ":null,"KCM":"大学英语中级(Ⅱ)","PX":null,"KCH":"FL006004"},{"PYFADM":"61ff62ed9a3a480eaf7ca0bbbe3e8bd0","XS":"32.0","KCXZDM_DISPLAY":"必修","WID":"C1CCC44EC91F05B0E0530D13AC0A4A70","XNXQ_DISPLAY":"2020-2021学年第一学期, 2021-2022学年第一学期","KKDWDM_DISPLAY":"外国语学院","BZ":null,"XXKC":null,"SFZGKC":"0","XF":"2.0","JHXNDM":null,"KSLXDM_DISPLAY":"考试","KCXZDM":"001","XDXQ":"1,3","SFZGKC_DISPLAY":"否","XDXNXQ":null,"KKDWDM":"1109","KSLXDM":"1","JHXQDM":null,"KZH":"3a0401dbd12547e38997f59d2ad4110c","KZM":"通识教育基础课","XNXQ":"2020-2021-1,2021-2022-1","CXXQ":null,"KCM":"高级英语(I)","PX":null,"KCH":"FL006005"},{"PYFADM":"61ff62ed9a3a480eaf7ca0bbbe3e8bd0","XS":"32.0","KCXZDM_DISPLAY":"必修","WID":"C1CCC44EC92B05B0E0530D13AC0A4A70","XNXQ_DISPLAY":"2020-2021学年第二学期, 2021-2022学年第二学期","KKDWDM_DISPLAY":"外国语学院","BZ":null,"XXKC":null,"SFZGKC":"0","XF":"2.0","JHXNDM":null,"KSLXDM_DISPLAY":"考试","KCXZDM":"001","XDXQ":"2,4","SFZGKC_DISPLAY":"否","XDXNXQ":null,"KKDWDM":"1109","KSLXDM":"1","JHXQDM":null,"KZH":"3a0401dbd12547e38997f59d2ad4110c","KZM":"通识教育基础课","XNXQ":"2020-2021-2,2021-2022-2","CXXQ":null,"KCM":"高级英语（Ⅱ）","PX":null,"KCH":"FL006006"},{"PYFADM":"61ff62ed9a3a480eaf7ca0bbbe3e8bd0","XS":"32.0","KCXZDM_DISPLAY":"学校限选","WID":"C1CCC44EC95505B0E0530D13AC0A4A70","XNXQ_DISPLAY":"2021-2022学年第二学期","KKDWDM_DISPLAY":"外国语学院","BZ":null,"XXKC":null,"SFZGKC":"0","XF":"2.0","JHXNDM":null,"KSLXDM_DISPLAY":"考试","KCXZDM":"011","XDXQ":"4","SFZGKC_DISPLAY":"否","XDXNXQ":null,"KKDWDM":"1109","KSLXDM":"1","JHXQDM":null,"KZH":"a27e6262bf8346dd83523b1dbee0ac83","KZM":"高级英语选修课程（2018级）","XNXQ":"2021-2022-2","CXXQ":null,"KCM":"高级口语","PX":null,"KCH":"FL006007"},{"PYFADM":"61ff62ed9a3a480eaf7ca0bbbe3e8bd0","XS":"32.0","KCXZDM_DISPLAY":"学校限选","WID":"C1CCC44EC95605B0E0530D13AC0A4A70","XNXQ_DISPLAY":"2021-2022学年第二学期","KKDWDM_DISPLAY":"外国语学院","BZ":null,"XXKC":null,"SFZGKC":"0","XF":"2.0","JHXNDM":null,"KSLXDM_DISPLAY":"考试","KCXZDM":"011","XDXQ":"4","SFZGKC_DISPLAY":"否","XDXNXQ":null,"KKDWDM":"1109","KSLXDM":"1","JHXQDM":null,"KZH":"a27e6262bf8346dd83523b1dbee0ac83","KZM":"高级英语选修课程（2018级）","XNXQ":"2021-2022-2","CXXQ":null,"KCM":"高级听力","PX":null,"KCH":"FL006008"},{"PYFADM":"61ff62ed9a3a480eaf7ca0bbbe3e8bd0","XS":"32.0","KCXZDM_DISPLAY":"学校限选","WID":"C1CCC44EC95705B0E0530D13AC0A4A70","XNXQ_DISPLAY":"2021-2022学年第二学期","KKDWDM_DISPLAY":"外国语学院","BZ":null,"XXKC":null,"SFZGKC":"0","XF":"2.0","JHXNDM":null,"KSLXDM_DISPLAY":"考试","KCXZDM":"011","XDXQ":"4","SFZGKC_DISPLAY":"否","XDXNXQ":null,"KKDWDM":"1109","KSLXDM":"1","JHXQDM":null,"KZH":"a27e6262bf8346dd83523b1dbee0ac83","KZM":"高级英语选修课程（2018级）","XNXQ":"2021-2022-2","CXXQ":null,"KCM":"高级写作","PX":null,"KCH":"FL006009"},{"PYFADM":"61ff62ed9a3a480eaf7ca0bbbe3e8bd0","XS":"32.0","KCXZDM_DISPLAY":"学校限选","WID":"C1CCC44EC90105B0E0530D13AC0A4A70","XNXQ_DISPLAY":"2022-2023学年第一学期","KKDWDM_DISPLAY":"外国语学院","BZ":null,"XXKC":null,"SFZGKC":"0","XF":"2.0","JHXNDM":null,"KSLXDM_DISPLAY":"考试","KCXZDM":"011","XDXQ":"5","SFZGKC_DISPLAY":"否","XDXNXQ":null,"KKDWDM":"1109","KSLXDM":"1","JHXQDM":null,"KZH":"a27e6262bf8346dd83523b1dbee0ac83","KZM":"高级英语选修课程（2018级）","XNXQ":"2022-2023-1","CXXQ":null,"KCM":"英美文化","PX":null,"KCH":"FL006010"},{"PYFADM":"61ff62ed9a3a480eaf7ca0bbbe3e8bd0","XS":"32.0","KCXZDM_DISPLAY":"学校限选","WID":"C1CCC44EC90205B0E0530D13AC0A4A70","XNXQ_DISPLAY":"2022-2023学年第一学期","KKDWDM_DISPLAY":"外国语学院","BZ":null,"XXKC":null,"SFZGKC":"0","XF":"2.0","JHXNDM":null,"KSLXDM_DISPLAY":"考试","KCXZDM":"011","XDXQ":"5","SFZGKC_DISPLAY":"否","XDXNXQ":null,"KKDWDM":"1109","KSLXDM":"1","JHXQDM":null,"KZH":"a27e6262bf8346dd83523b1dbee0ac83","KZM":"高级英语选修课程（2018级）","XNXQ":"2022-2023-1","CXXQ":null,"KCM":"英汉翻译","PX":null,"KCH":"FL006011"},{"PYFADM":"61ff62ed9a3a480eaf7ca0bbbe3e8bd0","XS":"32.0","KCXZDM_DISPLAY":"学校限选","WID":"C1CCC44EC90305B0E0530D13AC0A4A70","XNXQ_DISPLAY":"2021-2022学年第二学期","KKDWDM_DISPLAY":"外国语学院","BZ":null,"XXKC":null,"SFZGKC":"0","XF":"2.0","JHXNDM":null,"KSLXDM_DISPLAY":"考试","KCXZDM":"011","XDXQ":"4","SFZGKC_DISPLAY":"否","XDXNXQ":null,"KKDWDM":"1109","KSLXDM":"1","JHXQDM":null,"KZH":"a27e6262bf8346dd83523b1dbee0ac83","KZM":"高级英语选修课程（2018级）","XNXQ":"2021-2022-2","CXXQ":null,"KCM":"中国文化","PX":null,"KCH":"FL006012"},{"PYFADM":"61ff62ed9a3a480eaf7ca0bbbe3e8bd0","XS":"32.0","KCXZDM_DISPLAY":"学校限选","WID":"C1CCC44EC90405B0E0530D13AC0A4A70","XNXQ_DISPLAY":"2021-2022学年第二学期","KKDWDM_DISPLAY":"外国语学院","BZ":null,"XXKC":null,"SFZGKC":"0","XF":"2.0","JHXNDM":null,"KSLXDM_DISPLAY":"考试","KCXZDM":"011","XDXQ":"4","SFZGKC_DISPLAY":"否","XDXNXQ":null,"KKDWDM":"1109","KSLXDM":"1","JHXQDM":null,"KZH":"a27e6262bf8346dd83523b1dbee0ac83","KZM":"高级英语选修课程（2018级）","XNXQ":"2021-2022-2","CXXQ":null,"KCM":"科技英语阅读","PX":null,"KCH":"FL006013"},{"PYFADM":"61ff62ed9a3a480eaf7ca0bbbe3e8bd0","XS":"32.0","KCXZDM_DISPLAY":"学校限选","WID":"C1CCC44EC90505B0E0530D13AC0A4A70","XNXQ_DISPLAY":"2021-2022学年第二学期","KKDWDM_DISPLAY":"外国语学院","BZ":null,"XXKC":null,"SFZGKC":"0","XF":"2.0","JHXNDM":null,"KSLXDM_DISPLAY":"考试","KCXZDM":"011","XDXQ":"4","SFZGKC_DISPLAY":"否","XDXNXQ":null,"KKDWDM":"1109","KSLXDM":"1","JHXQDM":null,"KZH":"a27e6262bf8346dd83523b1dbee0ac83","KZM":"高级英语选修课程（2018级）","XNXQ":"2021-2022-2","CXXQ":null,"KCM":"科技英语写作","PX":null,"KCH":"FL006014"},{"PYFADM":"61ff62ed9a3a480eaf7ca0bbbe3e8bd0","XS":"32.0","KCXZDM_DISPLAY":"学校限选","WID":"C1CCC44EC90605B0E0530D13AC0A4A70","XNXQ_DISPLAY":"2021-2022学年第二学期","KKDWDM_DISPLAY":"外国语学院","BZ":null,"XXKC":null,"SFZGKC":"0","XF":"2.0","JHXNDM":null,"KSLXDM_DISPLAY":"考试","KCXZDM":"011","XDXQ":"4","SFZGKC_DISPLAY":"否","XDXNXQ":null,"KKDWDM":"1109","KSLXDM":"1","JHXQDM":null,"KZH":"a27e6262bf8346dd83523b1dbee0ac83","KZM":"高级英语选修课程（2018级）","XNXQ":"2021-2022-2","CXXQ":null,"KCM":"科技英语翻译","PX":null,"KCH":"FL006015"},{"PYFADM":"61ff62ed9a3a480eaf7ca0bbbe3e8bd0","XS":"32.0","KCXZDM_DISPLAY":"学校限选","WID":"C1CCC44EC90705B0E0530D13AC0A4A70","XNXQ_DISPLAY":"2021-2022学年第二学期","KKDWDM_DISPLAY":"外国语学院","BZ":null,"XXKC":null,"SFZGKC":"0","XF":"2.0","JHXNDM":null,"KSLXDM_DISPLAY":"考试","KCXZDM":"011","XDXQ":"4","SFZGKC_DISPLAY":"否","XDXNXQ":null,"KKDWDM":"1109","KSLXDM":"1","JHXQDM":null,"KZH":"a27e6262bf8346dd83523b1dbee0ac83","KZM":"高级英语选修课程（2018级）","XNXQ":"2021-2022-2","CXXQ":null,"KCM":"英文技术写作","PX":null,"KCH":"FL006016"},{"PYFADM":"61ff62ed9a3a480eaf7ca0bbbe3e8bd0","XS":"32.0","KCXZDM_DISPLAY":"学校限选","WID":"C1CCC44EC90805B0E0530D13AC0A4A70","XNXQ_DISPLAY":"2022-2023学年第一学期","KKDWDM_DISPLAY":"外国语学院","BZ":null,"XXKC":null,"SFZGKC":"0","XF":"2.0","JHXNDM":null,"KSLXDM_DISPLAY":"考试","KCXZDM":"011","XDXQ":"5","SFZGKC_DISPLAY":"否","XDXNXQ":null,"KKDWDM":"1109","KSLXDM":"1","JHXQDM":null,"KZH":"a27e6262bf8346dd83523b1dbee0ac83","KZM":"高级英语选修课程（2018级）","XNXQ":"2022-2023-1","CXXQ":null,"KCM":"商务英语","PX":null,"KCH":"FL006017"},{"PYFADM":"61ff62ed9a3a480eaf7ca0bbbe3e8bd0","XS":"32.0","KCXZDM_DISPLAY":"学校限选","WID":"C1CCC44EC90905B0E0530D13AC0A4A70","XNXQ_DISPLAY":"2022-2023学年第一学期","KKDWDM_DISPLAY":"外国语学院","BZ":null,"XXKC":null,"SFZGKC":"0","XF":"2.0","JHXNDM":null,"KSLXDM_DISPLAY":"考试","KCXZDM":"011","XDXQ":"5","SFZGKC_DISPLAY":"否","XDXNXQ":null,"KKDWDM":"1109","KSLXDM":"1","JHXQDM":null,"KZH":"a27e6262bf8346dd83523b1dbee0ac83","KZM":"高级英语选修课程（2018级）","XNXQ":"2022-2023-1","CXXQ":null,"KCM":"雅思英语","PX":null,"KCH":"FL006018"},{"PYFADM":"61ff62ed9a3a480eaf7ca0bbbe3e8bd0","XS":"32.0","KCXZDM_DISPLAY":"学校限选","WID":"C1CCC44EC90A05B0E0530D13AC0A4A70","XNXQ_DISPLAY":"2022-2023学年第一学期","KKDWDM_DISPLAY":"外国语学院","BZ":null,"XXKC":null,"SFZGKC":"0","XF":"2.0","JHXNDM":null,"KSLXDM_DISPLAY":"考试","KCXZDM":"011","XDXQ":"5","SFZGKC_DISPLAY":"否","XDXNXQ":null,"KKDWDM":"1109","KSLXDM":"1","JHXQDM":null,"KZH":"a27e6262bf8346dd83523b1dbee0ac83","KZM":"高级英语选修课程（2018级）","XNXQ":"2022-2023-1","CXXQ":null,"KCM":"托福英语","PX":null,"KCH":"FL006019"},{"PYFADM":"61ff62ed9a3a480eaf7ca0bbbe3e8bd0","XS":"32.0","KCXZDM_DISPLAY":"学校限选","WID":"C1CCC44EC93505B0E0530D13AC0A4A70","XNXQ_DISPLAY":"2021-2022学年第二学期","KKDWDM_DISPLAY":"外国语学院","BZ":null,"XXKC":null,"SFZGKC":"0","XF":"2.0","JHXNDM":null,"KSLXDM_DISPLAY":"考试","KCXZDM":"011","XDXQ":"4","SFZGKC_DISPLAY":"否","XDXNXQ":null,"KKDWDM":"1109","KSLXDM":"1","JHXQDM":null,"KZH":"a27e6262bf8346dd83523b1dbee0ac83","KZM":"高级英语选修课程（2018级）","XNXQ":"2021-2022-2","CXXQ":null,"KCM":"英语语言历史与文化","PX":null,"KCH":"FL006083"},{"PYFADM":"61ff62ed9a3a480eaf7ca0bbbe3e8bd0","XS":"32.0","KCXZDM_DISPLAY":"学校限选","WID":"C1CCC44EC93605B0E0530D13AC0A4A70","XNXQ_DISPLAY":"2021-2022学年第二学期","KKDWDM_DISPLAY":"外国语学院","BZ":null,"XXKC":null,"SFZGKC":"0","XF":"2.0","JHXNDM":null,"KSLXDM_DISPLAY":"考试","KCXZDM":"011","XDXQ":"4","SFZGKC_DISPLAY":"否","XDXNXQ":null,"KKDWDM":"1109","KSLXDM":"1","JHXQDM":null,"KZH":"a27e6262bf8346dd83523b1dbee0ac83","KZM":"高级英语选修课程（2018级）","XNXQ":"2021-2022-2","CXXQ":null,"KCM":"英文电影中的文化探析","PX":null,"KCH":"FL006084"},{"PYFADM":"61ff62ed9a3a480eaf7ca0bbbe3e8bd0","XS":"32.0","KCXZDM_DISPLAY":"学校限选","WID":"C1CCC44EC93805B0E0530D13AC0A4A70","XNXQ_DISPLAY":"2021-2022学年第二学期","KKDWDM_DISPLAY":"外国语学院","BZ":null,"XXKC":null,"SFZGKC":"0","XF":"2.0","JHXNDM":null,"KSLXDM_DISPLAY":"考试","KCXZDM":"011","XDXQ":"4","SFZGKC_DISPLAY":"否","XDXNXQ":null,"KKDWDM":"1109","KSLXDM":"1","JHXQDM":null,"KZH":"a27e6262bf8346dd83523b1dbee0ac83","KZM":"高级英语选修课程（2018级）","XNXQ":"2021-2022-2","CXXQ":null,"KCM":"大学学术英语：视听说","PX":null,"KCH":"FL006085"},{"PYFADM":"61ff62ed9a3a480eaf7ca0bbbe3e8bd0","XS":"32.0","KCXZDM_DISPLAY":"学校限选","WID":"C1CCC44EC94705B0E0530D13AC0A4A70","XNXQ_DISPLAY":"2021-2022学年第二学期","KKDWDM_DISPLAY":"外国语学院","BZ":null,"XXKC":null,"SFZGKC":"0","XF":"2.0","JHXNDM":null,"KSLXDM_DISPLAY":"考试","KCXZDM":"011","XDXQ":"4","SFZGKC_DISPLAY":"否","XDXNXQ":null,"KKDWDM":"1109","KSLXDM":"1","JHXQDM":null,"KZH":"a27e6262bf8346dd83523b1dbee0ac83","KZM":"高级英语选修课程（2018级）","XNXQ":"2021-2022-2","CXXQ":null,"KCM":"新实用汉译英翻译课程","PX":null,"KCH":"FL006089"},{"PYFADM":"61ff62ed9a3a480eaf7ca0bbbe3e8bd0","XS":"32.0","KCXZDM_DISPLAY":"学校限选","WID":"C1CCC44EC94805B0E0530D13AC0A4A70","XNXQ_DISPLAY":"2021-2022学年第二学期","KKDWDM_DISPLAY":"外国语学院","BZ":null,"XXKC":null,"SFZGKC":"0","XF":"2.0","JHXNDM":null,"KSLXDM_DISPLAY":"考试","KCXZDM":"011","XDXQ":"4","SFZGKC_DISPLAY":"否","XDXNXQ":null,"KKDWDM":"1109","KSLXDM":"1","JHXQDM":null,"KZH":"a27e6262bf8346dd83523b1dbee0ac83","KZM":"高级英语选修课程（2018级）","XNXQ":"2021-2022-2","CXXQ":null,"KCM":"高级阅读","PX":null,"KCH":"FL006090"},{"PYFADM":"61ff62ed9a3a480eaf7ca0bbbe3e8bd0","XS":"32.0","KCXZDM_DISPLAY":"学校限选","WID":"C1CCC44EC94905B0E0530D13AC0A4A70","XNXQ_DISPLAY":"2021-2022学年第二学期","KKDWDM_DISPLAY":"外国语学院","BZ":null,"XXKC":null,"SFZGKC":"0","XF":"2.0","JHXNDM":null,"KSLXDM_DISPLAY":"考试","KCXZDM":"011","XDXQ":"4","SFZGKC_DISPLAY":"否","XDXNXQ":null,"KKDWDM":"1109","KSLXDM":"1","JHXQDM":null,"KZH":"a27e6262bf8346dd83523b1dbee0ac83","KZM":"高级英语选修课程（2018级）","XNXQ":"2021-2022-2","CXXQ":null,"KCM":"跨文化交流英语","PX":null,"KCH":"FL006091"},{"PYFADM":"61ff62ed9a3a480eaf7ca0bbbe3e8bd0","XS":"32.0","KCXZDM_DISPLAY":"学校限选","WID":"C1CCC44EC94A05B0E0530D13AC0A4A70","XNXQ_DISPLAY":"2021-2022学年第二学期","KKDWDM_DISPLAY":"外国语学院","BZ":null,"XXKC":null,"SFZGKC":"0","XF":"2.0","JHXNDM":null,"KSLXDM_DISPLAY":"考试","KCXZDM":"011","XDXQ":"4","SFZGKC_DISPLAY":"否","XDXNXQ":null,"KKDWDM":"1109","KSLXDM":"1","JHXQDM":null,"KZH":"a27e6262bf8346dd83523b1dbee0ac83","KZM":"高级英语选修课程（2018级）","XNXQ":"2021-2022-2","CXXQ":null,"KCM":"新实用英美报刊阅读课程","PX":null,"KCH":"FL006092"},{"PYFADM":"61ff62ed9a3a480eaf7ca0bbbe3e8bd0","XS":"32.0","KCXZDM_DISPLAY":"学校限选","WID":"C1CCC44EC94B05B0E0530D13AC0A4A70","XNXQ_DISPLAY":"2021-2022学年第二学期","KKDWDM_DISPLAY":"外国语学院","BZ":null,"XXKC":null,"SFZGKC":"0","XF":"2.0","JHXNDM":null,"KSLXDM_DISPLAY":"考试","KCXZDM":"011","XDXQ":"4","SFZGKC_DISPLAY":"否","XDXNXQ":null,"KKDWDM":"1109","KSLXDM":"1","JHXQDM":null,"KZH":"a27e6262bf8346dd83523b1dbee0ac83","KZM":"高级英语选修课程（2018级）","XNXQ":"2021-2022-2","CXXQ":null,"KCM":"六级英语","PX":null,"KCH":"FL006093"},{"PYFADM":"61ff62ed9a3a480eaf7ca0bbbe3e8bd0","XS":"32.0","KCXZDM_DISPLAY":"学校限选","WID":"C1CCC44EC95805B0E0530D13AC0A4A70","XNXQ_DISPLAY":"2021-2022学年第一学期, 2021-2022学年第二学期","KKDWDM_DISPLAY":"外国语学院","BZ":null,"XXKC":null,"SFZGKC":"0","XF":"2.0","JHXNDM":null,"KSLXDM_DISPLAY":"考试","KCXZDM":"011","XDXQ":"3,4","SFZGKC_DISPLAY":"否","XDXNXQ":null,"KKDWDM":"1109","KSLXDM":"1","JHXQDM":null,"KZH":"a27e6262bf8346dd83523b1dbee0ac83","KZM":"高级英语选修课程（2018级）","XNXQ":"2021-2022-1,2021-2022-2","CXXQ":null,"KCM":"学术英语视听说","PX":null,"KCH":"FL006104"},{"PYFADM":"61ff62ed9a3a480eaf7ca0bbbe3e8bd0","XS":"4.8","KCXZDM_DISPLAY":"必修","WID":"C1CCC44EC95D05B0E0530D13AC0A4A70","XNXQ_DISPLAY":"2023-2024-2","KKDWDM_DISPLAY":"外国语学院","BZ":null,"XXKC":null,"SFZGKC":"0","XF":"0.3","JHXNDM":null,"KSLXDM_DISPLAY":"考试","KCXZDM":"001","XDXQ":"8","SFZGKC_DISPLAY":"否","XDXNXQ":null,"KKDWDM":"1109","KSLXDM":"1","JHXQDM":null,"KZH":"d506b8a6202a4464a5c605e2e8435de0","KZM":"英语四级（20级以后）","XNXQ":"2023-2024-2","CXXQ":null,"KCM":"国家英语四级","PX":null,"KCH":"FL007003"},{"PYFADM":"61ff62ed9a3a480eaf7ca0bbbe3e8bd0","XS":"4.8","KCXZDM_DISPLAY":"必修","WID":"C1CCC44EC95E05B0E0530D13AC0A4A70","XNXQ_DISPLAY":"2023-2024-2","KKDWDM_DISPLAY":"外国语学院","BZ":null,"XXKC":null,"SFZGKC":null,"XF":"0.3","JHXNDM":null,"KSLXDM_DISPLAY":"考试","KCXZDM":"001","XDXQ":"8","SFZGKC_DISPLAY":"","XDXNXQ":null,"KKDWDM":"1109","KSLXDM":"1","JHXQDM":null,"KZH":"d506b8a6202a4464a5c605e2e8435de0","KZM":"英语四级（20级以后）","XNXQ":"2023-2024-2","CXXQ":null,"KCM":"校内英语四级","PX":null,"KCH":"FL007004"},{"PYFADM":"61ff62ed9a3a480eaf7ca0bbbe3e8bd0","XS":"15.0","KCXZDM_DISPLAY":"必修","WID":"C1CCC44EC96405B0E0530D13AC0A4A70","XNXQ_DISPLAY":"2020-2021学年第一学期, 2020-2021学年第二学期, 2021-2022学年第一学期, 2021-2022学年第二学期, 2022-2023学年第一学期, 2022-2023学年第二学期, 2023-2024-1, 2023-2024-2","KKDWDM_DISPLAY":"体育部","BZ":null,"XXKC":null,"SFZGKC":null,"XF":"0.5","JHXNDM":null,"KSLXDM_DISPLAY":"考试","KCXZDM":"001","XDXQ":"1,2,3,4,5,6,7,8","SFZGKC_DISPLAY":"","XDXNXQ":null,"KKDWDM":"32","KSLXDM":"1","JHXQDM":null,"KZH":"3a0401dbd12547e38997f59d2ad4110c","KZM":"通识教育基础课","XNXQ":"2020-2021-1,2020-2021-2,2021-2022-1,2021-2022-2,2022-2023-1,2022-2023-2,2023-2024-1,2023-2024-2","CXXQ":null,"KCM":"大学体育(Ⅰ)","PX":null,"KCH":"HE006007"},{"PYFADM":"61ff62ed9a3a480eaf7ca0bbbe3e8bd0","XS":"15.0","KCXZDM_DISPLAY":"必修","WID":"C1CCC44EC96505B0E0530D13AC0A4A70","XNXQ_DISPLAY":"2020-2021学年第一学期, 2020-2021学年第二学期, 2021-2022学年第一学期, 2021-2022学年第二学期, 2022-2023学年第一学期, 2022-2023学年第二学期, 2023-2024-1, 2023-2024-2","KKDWDM_DISPLAY":"体育部","BZ":null,"XXKC":null,"SFZGKC":null,"XF":"0.5","JHXNDM":null,"KSLXDM_DISPLAY":"考试","KCXZDM":"001","XDXQ":"1,2,3,4,5,6,7,8","SFZGKC_DISPLAY":"","XDXNXQ":null,"KKDWDM":"32","KSLXDM":"1","JHXQDM":null,"KZH":"3a0401dbd12547e38997f59d2ad4110c","KZM":"通识教育基础课","XNXQ":"2020-2021-1,2020-2021-2,2021-2022-1,2021-2022-2,2022-2023-1,2022-2023-2,2023-2024-1,2023-2024-2","CXXQ":null,"KCM":"大学体育(Ⅱ)","PX":null,"KCH":"HE006008"},{"PYFADM":"61ff62ed9a3a480eaf7ca0bbbe3e8bd0","XS":"15.0","KCXZDM_DISPLAY":"必修","WID":"C1CCC44EC96605B0E0530D13AC0A4A70","XNXQ_DISPLAY":"2020-2021学年第一学期, 2020-2021学年第二学期, 2021-2022学年第一学期, 2021-2022学年第二学期, 2022-2023学年第一学期, 2022-2023学年第二学期, 2023-2024-1, 2023-2024-2","KKDWDM_DISPLAY":"体育部","BZ":null,"XXKC":null,"SFZGKC":null,"XF":"0.5","JHXNDM":null,"KSLXDM_DISPLAY":"考试","KCXZDM":"001","XDXQ":"1,2,3,4,5,6,7,8","SFZGKC_DISPLAY":"","XDXNXQ":null,"KKDWDM":"32","KSLXDM":"1","JHXQDM":null,"KZH":"3a0401dbd12547e38997f59d2ad4110c","KZM":"通识教育基础课","XNXQ":"2020-2021-1,2020-2021-2,2021-2022-1,2021-2022-2,2022-2023-1,2022-2023-2,2023-2024-1,2023-2024-2","CXXQ":null,"KCM":"大学体育(Ⅲ)","PX":null,"KCH":"HE006009"},{"PYFADM":"61ff62ed9a3a480eaf7ca0bbbe3e8bd0","XS":"15.0","KCXZDM_DISPLAY":"必修","WID":"C1CCC44EC96705B0E0530D13AC0A4A70","XNXQ_DISPLAY":"2020-2021学年第一学期, 2020-2021学年第二学期, 2021-2022学年第一学期, 2021-2022学年第二学期, 2022-2023学年第一学期, 2022-2023学年第二学期, 2023-2024-1, 2023-2024-2","KKDWDM_DISPLAY":"体育部","BZ":null,"XXKC":null,"SFZGKC":null,"XF":"0.5","JHXNDM":null,"KSLXDM_DISPLAY":"考试","KCXZDM":"001","XDXQ":"1,2,3,4,5,6,7,8","SFZGKC_DISPLAY":"","XDXNXQ":null,"KKDWDM":"32","KSLXDM":"1","JHXQDM":null,"KZH":"3a0401dbd12547e38997f59d2ad4110c","KZM":"通识教育基础课","XNXQ":"2020-2021-1,2020-2021-2,2021-2022-1,2021-2022-2,2022-2023-1,2022-2023-2,2023-2024-1,2023-2024-2","CXXQ":null,"KCM":"大学体育(Ⅳ)","PX":null,"KCH":"HE006010"},{"PYFADM":"61ff62ed9a3a480eaf7ca0bbbe3e8bd0","XS":"15.0","KCXZDM_DISPLAY":"必修","WID":"C1CCC44EC96805B0E0530D13AC0A4A70","XNXQ_DISPLAY":"2020-2021学年第一学期, 2020-2021学年第二学期, 2021-2022学年第一学期, 2021-2022学年第二学期, 2022-2023学年第一学期, 2022-2023学年第二学期, 2023-2024-1, 2023-2024-2","KKDWDM_DISPLAY":"体育部","BZ":null,"XXKC":null,"SFZGKC":null,"XF":"0.5","JHXNDM":null,"KSLXDM_DISPLAY":"考试","KCXZDM":"001","XDXQ":"1,2,3,4,5,6,7,8","SFZGKC_DISPLAY":"","XDXNXQ":null,"KKDWDM":"32","KSLXDM":"1","JHXQDM":null,"KZH":"3a0401dbd12547e38997f59d2ad4110c","KZM":"通识教育基础课","XNXQ":"2020-2021-1,2020-2021-2,2021-2022-1,2021-2022-2,2022-2023-1,2022-2023-2,2023-2024-1,2023-2024-2","CXXQ":null,"KCM":"大学体育(Ⅴ)","PX":null,"KCH":"HE006011"},{"PYFADM":"61ff62ed9a3a480eaf7ca0bbbe3e8bd0","XS":"15.0","KCXZDM_DISPLAY":"必修","WID":"C1CCC44EC96905B0E0530D13AC0A4A70","XNXQ_DISPLAY":"2020-2021学年第一学期, 2020-2021学年第二学期, 2021-2022学年第一学期, 2021-2022学年第二学期, 2022-2023学年第一学期, 2022-2023学年第二学期, 2023-2024-1, 2023-2024-2","KKDWDM_DISPLAY":"体育部","BZ":null,"XXKC":null,"SFZGKC":null,"XF":"0.5","JHXNDM":null,"KSLXDM_DISPLAY":"考试","KCXZDM":"001","XDXQ":"1,2,3,4,5,6,7,8","SFZGKC_DISPLAY":"","XDXNXQ":null,"KKDWDM":"32","KSLXDM":"1","JHXQDM":null,"KZH":"3a0401dbd12547e38997f59d2ad4110c","KZM":"通识教育基础课","XNXQ":"2020-2021-1,2020-2021-2,2021-2022-1,2021-2022-2,2022-2023-1,2022-2023-2,2023-2024-1,2023-2024-2","CXXQ":null,"KCM":"大学体育(Ⅵ)","PX":null,"KCH":"HE006012"},{"PYFADM":"61ff62ed9a3a480eaf7ca0bbbe3e8bd0","XS":"15.0","KCXZDM_DISPLAY":"必修","WID":"C1CCC44EC96A05B0E0530D13AC0A4A70","XNXQ_DISPLAY":"2020-2021学年第一学期, 2020-2021学年第二学期, 2021-2022学年第一学期, 2021-2022学年第二学期, 2022-2023学年第一学期, 2022-2023学年第二学期, 2023-2024-1, 2023-2024-2","KKDWDM_DISPLAY":"体育部","BZ":null,"XXKC":null,"SFZGKC":null,"XF":"0.5","JHXNDM":null,"KSLXDM_DISPLAY":"考试","KCXZDM":"001","XDXQ":"1,2,3,4,5,6,7,8","SFZGKC_DISPLAY":"","XDXNXQ":null,"KKDWDM":"32","KSLXDM":"1","JHXQDM":null,"KZH":"3a0401dbd12547e38997f59d2ad4110c","KZM":"通识教育基础课","XNXQ":"2020-2021-1,2020-2021-2,2021-2022-1,2021-2022-2,2022-2023-1,2022-2023-2,2023-2024-1,2023-2024-2","CXXQ":null,"KCM":"大学体育(Ⅶ)","PX":null,"KCH":"HE006013"},{"PYFADM":"61ff62ed9a3a480eaf7ca0bbbe3e8bd0","XS":"15.0","KCXZDM_DISPLAY":"必修","WID":"C1CCC44EC96B05B0E0530D13AC0A4A70","XNXQ_DISPLAY":"2020-2021学年第一学期, 2020-2021学年第二学期, 2021-2022学年第一学期, 2021-2022学年第二学期, 2022-2023学年第一学期, 2022-2023学年第二学期, 2023-2024-1, 2023-2024-2","KKDWDM_DISPLAY":"体育部","BZ":null,"XXKC":null,"SFZGKC":null,"XF":"0.5","JHXNDM":null,"KSLXDM_DISPLAY":"考试","KCXZDM":"001","XDXQ":"1,2,3,4,5,6,7,8","SFZGKC_DISPLAY":"","XDXNXQ":null,"KKDWDM":"32","KSLXDM":"1","JHXQDM":null,"KZH":"3a0401dbd12547e38997f59d2ad4110c","KZM":"通识教育基础课","XNXQ":"2020-2021-1,2020-2021-2,2021-2022-1,2021-2022-2,2022-2023-1,2022-2023-2,2023-2024-1,2023-2024-2","CXXQ":null,"KCM":"大学体育(Ⅷ)","PX":null,"KCH":"HE006014"},{"PYFADM":"61ff62ed9a3a480eaf7ca0bbbe3e8bd0","XS":"3.2","KCXZDM_DISPLAY":"必修","WID":"E27844CF2DB75167E0530D13AC0A53E6","XNXQ_DISPLAY":"2023-2024-2","KKDWDM_DISPLAY":"体育部","BZ":null,"XXKC":null,"SFZGKC":"0","XF":"0.2","JHXNDM":null,"KSLXDM_DISPLAY":"考查","KCXZDM":"001","XDXQ":"8","SFZGKC_DISPLAY":"否","XDXNXQ":null,"KKDWDM":"32","KSLXDM":"2","JHXQDM":null,"KZH":"525a2f8f4397457098a4ab3d7c4abd53","KZM":"体育能力达标测试2021","XNXQ":"2023-2024-2","CXXQ":null,"KCM":"体育能力达标测试","PX":null,"KCH":"HE006016"},{"PYFADM":"61ff62ed9a3a480eaf7ca0bbbe3e8bd0","XS":"2.0","KCXZDM_DISPLAY":"必修","WID":"C1CCC44EC96105B0E0530D13AC0A4A70","XNXQ_DISPLAY":"2020-2021学年第二学期, 2021-2022学年第一学期, 2021-2022学年第二学期, 2022-2023学年第一学期, 2022-2023学年第二学期, 2023-2024-1, 2023-2024-2","KKDWDM_DISPLAY":"电子信息与通信工程学科专业实验中心","BZ":null,"XXKC":null,"SFZGKC":null,"XF":"0.1","JHXNDM":null,"KSLXDM_DISPLAY":"考查","KCXZDM":"001","XDXQ":"2,3,4,5,6,7,8","SFZGKC_DISPLAY":"","XDXNXQ":null,"KKDWDM":"1311","KSLXDM":"2","JHXQDM":null,"KZH":"afe6bdf5f641498aa18478953fe04516","KZM":"实验实践能力达标测试（理工）","XNXQ":"2020-2021-2,2021-2022-1,2021-2022-2,2022-2023-1,2022-2023-2,2023-2024-1,2023-2024-2","CXXQ":null,"KCM":"实验实践能力达标测试C1-1（理工科计算机）","PX":null,"KCH":"II006020"},{"PYFADM":"61ff62ed9a3a480eaf7ca0bbbe3e8bd0","XS":"2.0","KCXZDM_DISPLAY":"必修","WID":"C1CCC44EC95F05B0E0530D13AC0A4A70","XNXQ_DISPLAY":"2020-2021学年第二学期, 2021-2022学年第一学期, 2021-2022学年第二学期, 2022-2023学年第一学期, 2022-2023学年第二学期, 2023-2024-1, 2023-2024-2","KKDWDM_DISPLAY":"电子信息与通信工程学科专业实验中心","BZ":null,"XXKC":null,"SFZGKC":null,"XF":"0.1","JHXNDM":null,"KSLXDM_DISPLAY":"考查","KCXZDM":"001","XDXQ":"2,3,4,5,6,7,8","SFZGKC_DISPLAY":"","XDXNXQ":null,"KKDWDM":"1311","KSLXDM":"2","JHXQDM":null,"KZH":"afe6bdf5f641498aa18478953fe04516","KZM":"实验实践能力达标测试（理工）","XNXQ":"2020-2021-2,2021-2022-1,2021-2022-2,2022-2023-1,2022-2023-2,2023-2024-1,2023-2024-2","CXXQ":null,"KCM":"实验实践能力达标测试C1-2（理工科物理）","PX":null,"KCH":"II006022"},{"PYFADM":"61ff62ed9a3a480eaf7ca0bbbe3e8bd0","XS":"2.0","KCXZDM_DISPLAY":"必修","WID":"C1CCC44EC96005B0E0530D13AC0A4A70","XNXQ_DISPLAY":"2020-2021学年第二学期, 2021-2022学年第一学期, 2021-2022学年第二学期, 2022-2023学年第一学期, 2022-2023学年第二学期, 2023-2024-1, 2023-2024-2","KKDWDM_DISPLAY":"电子信息与通信工程学科专业实验中心","BZ":null,"XXKC":null,"SFZGKC":null,"XF":"0.1","JHXNDM":null,"KSLXDM_DISPLAY":"考查","KCXZDM":"001","XDXQ":"2,3,4,5,6,7,8","SFZGKC_DISPLAY":"","XDXNXQ":null,"KKDWDM":"1311","KSLXDM":"2","JHXQDM":null,"KZH":"afe6bdf5f641498aa18478953fe04516","KZM":"实验实践能力达标测试（理工）","XNXQ":"2020-2021-2,2021-2022-1,2021-2022-2,2022-2023-1,2022-2023-2,2023-2024-1,2023-2024-2","CXXQ":null,"KCM":"实验实践能力达标测试C2","PX":null,"KCH":"II006023"},{"PYFADM":"61ff62ed9a3a480eaf7ca0bbbe3e8bd0","XS":"2.0","KCXZDM_DISPLAY":"必修","WID":"C1CCC44EC96205B0E0530D13AC0A4A70","XNXQ_DISPLAY":"2020-2021学年第二学期, 2021-2022学年第一学期, 2021-2022学年第二学期, 2022-2023学年第一学期, 2022-2023学年第二学期, 2023-2024-1, 2023-2024-2","KKDWDM_DISPLAY":"电子信息与通信工程学科专业实验中心","BZ":null,"XXKC":null,"SFZGKC":null,"XF":"0.1","JHXNDM":null,"KSLXDM_DISPLAY":"考查","KCXZDM":"001","XDXQ":"2,3,4,5,6,7,8","SFZGKC_DISPLAY":"","XDXNXQ":null,"KKDWDM":"1311","KSLXDM":"2","JHXQDM":null,"KZH":"afe6bdf5f641498aa18478953fe04516","KZM":"实验实践能力达标测试（理工）","XNXQ":"2020-2021-2,2021-2022-1,2021-2022-2,2022-2023-1,2022-2023-2,2023-2024-1,2023-2024-2","CXXQ":null,"KCM":"实验实践能力达标测试B","PX":null,"KCH":"II006024"},{"PYFADM":"61ff62ed9a3a480eaf7ca0bbbe3e8bd0","XS":"2.0","KCXZDM_DISPLAY":"必修","WID":"C1CCC44EC96305B0E0530D13AC0A4A70","XNXQ_DISPLAY":"2020-2021学年第二学期, 2021-2022学年第一学期, 2021-2022学年第二学期, 2022-2023学年第一学期, 2022-2023学年第二学期, 2023-2024-1, 2023-2024-2","KKDWDM_DISPLAY":"电子信息与通信工程学科专业实验中心","BZ":null,"XXKC":null,"SFZGKC":null,"XF":"0.1","JHXNDM":null,"KSLXDM_DISPLAY":"考查","KCXZDM":"001","XDXQ":"2,3,4,5,6,7,8","SFZGKC_DISPLAY":"","XDXNXQ":null,"KKDWDM":"1311","KSLXDM":"2","JHXQDM":null,"KZH":"afe6bdf5f641498aa18478953fe04516","KZM":"实验实践能力达标测试（理工）","XNXQ":"2020-2021-2,2021-2022-1,2021-2022-2,2022-2023-1,2022-2023-2,2023-2024-1,2023-2024-2","CXXQ":null,"KCM":"实验实践能力达标测试A","PX":null,"KCH":"II006025"},{"PYFADM":"61ff62ed9a3a480eaf7ca0bbbe3e8bd0","XS":"48.0","KCXZDM_DISPLAY":"必修","WID":"C1CCC44EC92005B0E0530D13AC0A4A70","XNXQ_DISPLAY":"2020-2021学年第一学期","KKDWDM_DISPLAY":"马克思主义学院","BZ":null,"XXKC":null,"SFZGKC":null,"XF":"3.0","JHXNDM":null,"KSLXDM_DISPLAY":"考试","KCXZDM":"001","XDXQ":"1","SFZGKC_DISPLAY":"","XDXNXQ":null,"KKDWDM":"1119","KSLXDM":"1","JHXQDM":null,"KZH":"3a0401dbd12547e38997f59d2ad4110c","KZM":"通识教育基础课","XNXQ":"2020-2021-1","CXXQ":null,"KCM":"思想道德与法治","PX":null,"KCH":"MC006001"},{"PYFADM":"61ff62ed9a3a480eaf7ca0bbbe3e8bd0","XS":"48.0","KCXZDM_DISPLAY":"必修","WID":"C1CCC44EC92505B0E0530D13AC0A4A70","XNXQ_DISPLAY":"2020-2021学年第二学期","KKDWDM_DISPLAY":"马克思主义学院","BZ":null,"XXKC":null,"SFZGKC":null,"XF":"3.0","JHXNDM":null,"KSLXDM_DISPLAY":"考试","KCXZDM":"001","XDXQ":"2","SFZGKC_DISPLAY":"","XDXNXQ":null,"KKDWDM":"1119","KSLXDM":"1","JHXQDM":null,"KZH":"3a0401dbd12547e38997f59d2ad4110c","KZM":"通识教育基础课","XNXQ":"2020-2021-2","CXXQ":null,"KCM":"中国近现代史纲要","PX":null,"KCH":"MC006002"},{"PYFADM":"61ff62ed9a3a480eaf7ca0bbbe3e8bd0","XS":"48.0","KCXZDM_DISPLAY":"必修","WID":"C1CCC44EC95405B0E0530D13AC0A4A70","XNXQ_DISPLAY":"2021-2022学年第一学期","KKDWDM_DISPLAY":"马克思主义学院","BZ":null,"XXKC":null,"SFZGKC":"0","XF":"3.0","JHXNDM":null,"KSLXDM_DISPLAY":"考试","KCXZDM":"001","XDXQ":"3","SFZGKC_DISPLAY":"否","XDXNXQ":null,"KKDWDM":"1119","KSLXDM":"1","JHXQDM":null,"KZH":"3a0401dbd12547e38997f59d2ad4110c","KZM":"通识教育基础课","XNXQ":"2021-2022-1","CXXQ":null,"KCM":"马克思主义基本原理","PX":null,"KCH":"MC006003"},{"PYFADM":"61ff62ed9a3a480eaf7ca0bbbe3e8bd0","XS":"48.0","KCXZDM_DISPLAY":"","WID":"C1CCC44EC91205B0E0530D13AC0A4A70","XNXQ_DISPLAY":"2021-2022学年第二学期","KKDWDM_DISPLAY":"马克思主义学院","BZ":null,"XXKC":null,"SFZGKC":"0","XF":"3.0","JHXNDM":null,"KSLXDM_DISPLAY":"考试","KCXZDM":null,"XDXQ":"4","SFZGKC_DISPLAY":"否","XDXNXQ":null,"KKDWDM":"1119","KSLXDM":"1","JHXQDM":null,"KZH":"3a0401dbd12547e38997f59d2ad4110c","KZM":"通识教育基础课","XNXQ":"2021-2022-2","CXXQ":null,"KCM":"毛泽东思想和中国特色社会主义理论体系概论","PX":null,"KCH":"MC006004"},{"PYFADM":"61ff62ed9a3a480eaf7ca0bbbe3e8bd0","XS":"8.0","KCXZDM_DISPLAY":"必修","WID":"C1CCC44EC92105B0E0530D13AC0A4A70","XNXQ_DISPLAY":"2020-2021学年第一学期","KKDWDM_DISPLAY":"马克思主义学院","BZ":null,"XXKC":null,"SFZGKC":null,"XF":"0.3","JHXNDM":null,"KSLXDM_DISPLAY":"考查","KCXZDM":"001","XDXQ":"1","SFZGKC_DISPLAY":"","XDXNXQ":null,"KKDWDM":"1119","KSLXDM":"2","JHXQDM":null,"KZH":"3a0401dbd12547e38997f59d2ad4110c","KZM":"通识教育基础课","XNXQ":"2020-2021-1","CXXQ":null,"KCM":"形势与政策(Ⅰ)","PX":null,"KCH":"MC006005-1"},{"PYFADM":"61ff62ed9a3a480eaf7ca0bbbe3e8bd0","XS":"8.0","KCXZDM_DISPLAY":"必修","WID":"C1CCC44EC92605B0E0530D13AC0A4A70","XNXQ_DISPLAY":"2020-2021学年第二学期","KKDWDM_DISPLAY":"马克思主义学院","BZ":null,"XXKC":null,"SFZGKC":null,"XF":"0.3","JHXNDM":null,"KSLXDM_DISPLAY":"考查","KCXZDM":"001","XDXQ":"2","SFZGKC_DISPLAY":"","XDXNXQ":null,"KKDWDM":"1119","KSLXDM":"2","JHXQDM":null,"KZH":"3a0401dbd12547e38997f59d2ad4110c","KZM":"通识教育基础课","XNXQ":"2020-2021-2","CXXQ":null,"KCM":"形势与政策(Ⅱ)","PX":null,"KCH":"MC006005-2"},{"PYFADM":"61ff62ed9a3a480eaf7ca0bbbe3e8bd0","XS":"8.0","KCXZDM_DISPLAY":"必修","WID":"C1CCC44EC92805B0E0530D13AC0A4A70","XNXQ_DISPLAY":"2021-2022学年第一学期","KKDWDM_DISPLAY":"马克思主义学院","BZ":null,"XXKC":null,"SFZGKC":null,"XF":"0.3","JHXNDM":null,"KSLXDM_DISPLAY":"考查","KCXZDM":"001","XDXQ":"3","SFZGKC_DISPLAY":"","XDXNXQ":null,"KKDWDM":"1119","KSLXDM":"2","JHXQDM":null,"KZH":"3a0401dbd12547e38997f59d2ad4110c","KZM":"通识教育基础课","XNXQ":"2021-2022-1","CXXQ":null,"KCM":"形势与政策(Ⅲ)","PX":null,"KCH":"MC006005-3"},{"PYFADM":"61ff62ed9a3a480eaf7ca0bbbe3e8bd0","XS":"8.0","KCXZDM_DISPLAY":"必修","WID":"C1CCC44EC92905B0E0530D13AC0A4A70","XNXQ_DISPLAY":"2021-2022学年第二学期","KKDWDM_DISPLAY":"马克思主义学院","BZ":null,"XXKC":null,"SFZGKC":null,"XF":"0.3","JHXNDM":null,"KSLXDM_DISPLAY":"考查","KCXZDM":"001","XDXQ":"4","SFZGKC_DISPLAY":"","XDXNXQ":null,"KKDWDM":"1119","KSLXDM":"2","JHXQDM":null,"KZH":"3a0401dbd12547e38997f59d2ad4110c","KZM":"通识教育基础课","XNXQ":"2021-2022-2","CXXQ":null,"KCM":"形势与政策(Ⅳ)","PX":null,"KCH":"MC006005-4"},{"PYFADM":"61ff62ed9a3a480eaf7ca0bbbe3e8bd0","XS":"8.0","KCXZDM_DISPLAY":"必修","WID":"C1CCC44EC95905B0E0530D13AC0A4A70","XNXQ_DISPLAY":"2022-2023学年第一学期","KKDWDM_DISPLAY":"马克思主义学院","BZ":null,"XXKC":null,"SFZGKC":null,"XF":"0.2","JHXNDM":null,"KSLXDM_DISPLAY":"考查","KCXZDM":"001","XDXQ":"5","SFZGKC_DISPLAY":"","XDXNXQ":null,"KKDWDM":"1119","KSLXDM":"2","JHXQDM":null,"KZH":"3a0401dbd12547e38997f59d2ad4110c","KZM":"通识教育基础课","XNXQ":"2022-2023-1","CXXQ":null,"KCM":"形势与政策(Ⅴ)","PX":null,"KCH":"MC006005-5"},{"PYFADM":"61ff62ed9a3a480eaf7ca0bbbe3e8bd0","XS":"8.0","KCXZDM_DISPLAY":"必修","WID":"C1CCC44EC95A05B0E0530D13AC0A4A70","XNXQ_DISPLAY":"2022-2023学年第二学期","KKDWDM_DISPLAY":"马克思主义学院","BZ":null,"XXKC":null,"SFZGKC":null,"XF":"0.2","JHXNDM":null,"KSLXDM_DISPLAY":"考查","KCXZDM":"001","XDXQ":"6","SFZGKC_DISPLAY":"","XDXNXQ":null,"KKDWDM":"1119","KSLXDM":"2","JHXQDM":null,"KZH":"3a0401dbd12547e38997f59d2ad4110c","KZM":"通识教育基础课","XNXQ":"2022-2023-2","CXXQ":null,"KCM":"形势与政策(Ⅵ)","PX":null,"KCH":"MC006005-6"},{"PYFADM":"61ff62ed9a3a480eaf7ca0bbbe3e8bd0","XS":"8.0","KCXZDM_DISPLAY":"必修","WID":"C1CCC44EC95B05B0E0530D13AC0A4A70","XNXQ_DISPLAY":"2023-2024-1","KKDWDM_DISPLAY":"马克思主义学院","BZ":null,"XXKC":null,"SFZGKC":null,"XF":"0.2","JHXNDM":null,"KSLXDM_DISPLAY":"考查","KCXZDM":"001","XDXQ":"7","SFZGKC_DISPLAY":"","XDXNXQ":null,"KKDWDM":"1119","KSLXDM":"2","JHXQDM":null,"KZH":"3a0401dbd12547e38997f59d2ad4110c","KZM":"通识教育基础课","XNXQ":"2023-2024-1","CXXQ":null,"KCM":"形势与政策(Ⅶ)","PX":null,"KCH":"MC006005-7"},{"PYFADM":"61ff62ed9a3a480eaf7ca0bbbe3e8bd0","XS":"8.0","KCXZDM_DISPLAY":"必修","WID":"C1CCC44EC95C05B0E0530D13AC0A4A70","XNXQ_DISPLAY":"2023-2024-2","KKDWDM_DISPLAY":"马克思主义学院","BZ":null,"XXKC":null,"SFZGKC":null,"XF":"0.2","JHXNDM":null,"KSLXDM_DISPLAY":"考查","KCXZDM":"001","XDXQ":"8","SFZGKC_DISPLAY":"","XDXNXQ":null,"KKDWDM":"1119","KSLXDM":"2","JHXQDM":null,"KZH":"3a0401dbd12547e38997f59d2ad4110c","KZM":"通识教育基础课","XNXQ":"2023-2024-2","CXXQ":null,"KCM":"形势与政策(Ⅷ)","PX":null,"KCH":"MC006005-8"},{"PYFADM":"61ff62ed9a3a480eaf7ca0bbbe3e8bd0","XS":"16.0","KCXZDM_DISPLAY":"必修","WID":"C1CCC44EC92705B0E0530D13AC0A4A70","XNXQ_DISPLAY":"2020-2021学年第二学期","KKDWDM_DISPLAY":"大学生心理健康教育","BZ":null,"XXKC":null,"SFZGKC":null,"XF":"1.0","JHXNDM":null,"KSLXDM_DISPLAY":"考查","KCXZDM":"001","XDXQ":"2","SFZGKC_DISPLAY":"","XDXNXQ":null,"KKDWDM":"1310","KSLXDM":"2","JHXQDM":null,"KZH":"3a0401dbd12547e38997f59d2ad4110c","KZM":"通识教育基础课","XNXQ":"2020-2021-2","CXXQ":null,"KCM":"大学生心理健康教育","PX":null,"KCH":"MC006006"},{"PYFADM":"61ff62ed9a3a480eaf7ca0bbbe3e8bd0","XS":"32.0","KCXZDM_DISPLAY":"必修","WID":"C1CCC44EC95305B0E0530D13AC0A4A70","XNXQ_DISPLAY":"2021-2022学年第二学期","KKDWDM_DISPLAY":"马克思主义学院","BZ":null,"XXKC":null,"SFZGKC":"0","XF":"2.0","JHXNDM":null,"KSLXDM_DISPLAY":"考查","KCXZDM":"001","XDXQ":"4","SFZGKC_DISPLAY":"否","XDXNXQ":null,"KKDWDM":"1119","KSLXDM":"2","JHXQDM":null,"KZH":"3a0401dbd12547e38997f59d2ad4110c","KZM":"通识教育基础课","XNXQ":"2021-2022-2","CXXQ":null,"KCM":"思想政治理论实践课","PX":null,"KCH":"MC006007"},{"PYFADM":"61ff62ed9a3a480eaf7ca0bbbe3e8bd0","XS":"32.0","KCXZDM_DISPLAY":"必修","WID":"34ac05e7ded94bad88a8d53b20138e92","XNXQ_DISPLAY":"2021-2022学年第二学期, 2022-2023学年第一学期","KKDWDM_DISPLAY":"马克思主义学院","BZ":null,"XXKC":null,"SFZGKC":"0","XF":"2.0","JHXNDM":null,"KSLXDM_DISPLAY":"考试","KCXZDM":"001","XDXQ":"4,5","SFZGKC_DISPLAY":"否","XDXNXQ":null,"KKDWDM":"1119","KSLXDM":"1","JHXQDM":null,"KZH":"3a0401dbd12547e38997f59d2ad4110c","KZM":"通识教育基础课","XNXQ":"2021-2022-2,2022-2023-1","CXXQ":null,"KCM":"习近平新时代中国特色社会主义思想概论","PX":null,"KCH":"MC006019"},{"PYFADM":"61ff62ed9a3a480eaf7ca0bbbe3e8bd0","XS":"48.0","KCXZDM_DISPLAY":"必修","WID":"C1CCC44EC90B05B0E0530D13AC0A4A70","XNXQ_DISPLAY":"2021-2022学年第一学期","KKDWDM_DISPLAY":"数学与统计学院","BZ":null,"XXKC":null,"SFZGKC":"0","XF":"3.0","JHXNDM":null,"KSLXDM_DISPLAY":"考试","KCXZDM":"001","XDXQ":"3","SFZGKC_DISPLAY":"否","XDXNXQ":null,"KKDWDM":"1107","KSLXDM":"1","JHXQDM":null,"KZH":"2018060003_ggkz","KZM":"大类基础课","XNXQ":"2021-2022-1","CXXQ":null,"KCM":"常微分方程","PX":null,"KCH":"MS202007"},{"PYFADM":"61ff62ed9a3a480eaf7ca0bbbe3e8bd0","XS":"48.0","KCXZDM_DISPLAY":"必修","WID":"C1CCC44EC91005B0E0530D13AC0A4A70","XNXQ_DISPLAY":"2021-2022学年第一学期","KKDWDM_DISPLAY":"数学与统计学院","BZ":null,"XXKC":null,"SFZGKC":"0","XF":"3.0","JHXNDM":null,"KSLXDM_DISPLAY":"考试","KCXZDM":"001","XDXQ":"3","SFZGKC_DISPLAY":"否","XDXNXQ":null,"KKDWDM":"1107","KSLXDM":"1","JHXQDM":null,"KZH":"2018060003_ggkz","KZM":"大类基础课","XNXQ":"2021-2022-1","CXXQ":null,"KCM":"复变函数","PX":null,"KCH":"MS202008"},{"PYFADM":"61ff62ed9a3a480eaf7ca0bbbe3e8bd0","XS":"48.0","KCXZDM_DISPLAY":"必修","WID":"C1CCC44EC91105B0E0530D13AC0A4A70","XNXQ_DISPLAY":"2021-2022学年第二学期","KKDWDM_DISPLAY":"数学与统计学院","BZ":null,"XXKC":null,"SFZGKC":"0","XF":"3.0","JHXNDM":null,"KSLXDM_DISPLAY":"考试","KCXZDM":"001","XDXQ":"4","SFZGKC_DISPLAY":"否","XDXNXQ":null,"KKDWDM":"1107","KSLXDM":"1","JHXQDM":null,"KZH":"2018060003_ggkz","KZM":"大类基础课","XNXQ":"2021-2022-2","CXXQ":null,"KCM":"实变函数","PX":null,"KCH":"MS202009"},{"PYFADM":"61ff62ed9a3a480eaf7ca0bbbe3e8bd0","XS":"96.0","KCXZDM_DISPLAY":"必修","WID":"9d80ddd2468e46869eaa655f705875b9","XNXQ_DISPLAY":"2020-2021学年第一学期","KKDWDM_DISPLAY":"数学与统计学院","BZ":null,"XXKC":null,"SFZGKC":null,"XF":"6.0","JHXNDM":null,"KSLXDM_DISPLAY":"考试","KCXZDM":"001","XDXQ":"1","SFZGKC_DISPLAY":"","XDXNXQ":null,"KKDWDM":"1107","KSLXDM":"1","JHXQDM":null,"KZH":"2018060003_ggkz","KZM":"大类基础课","XNXQ":"2020-2021-1","CXXQ":null,"KCM":"数学分析（I）","PX":null,"KCH":"MS202061"},{"PYFADM":"61ff62ed9a3a480eaf7ca0bbbe3e8bd0","XS":"80.0","KCXZDM_DISPLAY":"必修","WID":"c396549bf6a34a77926c866bec2860ed","XNXQ_DISPLAY":"2020-2021学年第二学期","KKDWDM_DISPLAY":"数学与统计学院","BZ":null,"XXKC":null,"SFZGKC":null,"XF":"5.0","JHXNDM":null,"KSLXDM_DISPLAY":"考试","KCXZDM":"001","XDXQ":"2","SFZGKC_DISPLAY":"","XDXNXQ":null,"KKDWDM":"1107","KSLXDM":"1","JHXQDM":null,"KZH":"2018060003_ggkz","KZM":"大类基础课","XNXQ":"2020-2021-2","CXXQ":null,"KCM":"数学分析（II）","PX":null,"KCH":"MS202062"},{"PYFADM":"61ff62ed9a3a480eaf7ca0bbbe3e8bd0","XS":"80.0","KCXZDM_DISPLAY":"必修","WID":"9da588bb35274d69910391cff344db84","XNXQ_DISPLAY":"2021-2022学年第一学期","KKDWDM_DISPLAY":"数学与统计学院","BZ":null,"XXKC":null,"SFZGKC":null,"XF":"5.0","JHXNDM":null,"KSLXDM_DISPLAY":"考试","KCXZDM":"001","XDXQ":"3","SFZGKC_DISPLAY":"","XDXNXQ":null,"KKDWDM":"1107","KSLXDM":"1","JHXQDM":null,"KZH":"2018060003_ggkz","KZM":"大类基础课","XNXQ":"2021-2022-1","CXXQ":null,"KCM":"数学分析（III）","PX":null,"KCH":"MS202063"},{"PYFADM":"61ff62ed9a3a480eaf7ca0bbbe3e8bd0","XS":"64.0","KCXZDM_DISPLAY":"必修","WID":"cb99dcada5be46c49bf67e1d9dde6b86","XNXQ_DISPLAY":"2020-2021学年第一学期","KKDWDM_DISPLAY":"数学与统计学院","BZ":null,"XXKC":null,"SFZGKC":null,"XF":"4.0","JHXNDM":null,"KSLXDM_DISPLAY":"考试","KCXZDM":"001","XDXQ":"1","SFZGKC_DISPLAY":"","XDXNXQ":null,"KKDWDM":"1107","KSLXDM":"1","JHXQDM":null,"KZH":"2018060003_ggkz","KZM":"大类基础课","XNXQ":"2020-2021-1","CXXQ":null,"KCM":"高等代数（I）","PX":null,"KCH":"MS202064"},{"PYFADM":"61ff62ed9a3a480eaf7ca0bbbe3e8bd0","XS":"80.0","KCXZDM_DISPLAY":"必修","WID":"60b35daaad8741ef945f562da459d7e5","XNXQ_DISPLAY":"2020-2021学年第二学期","KKDWDM_DISPLAY":"数学与统计学院","BZ":null,"XXKC":null,"SFZGKC":null,"XF":"5.0","JHXNDM":null,"KSLXDM_DISPLAY":"考试","KCXZDM":"001","XDXQ":"2","SFZGKC_DISPLAY":"","XDXNXQ":null,"KKDWDM":"1107","KSLXDM":"1","JHXQDM":null,"KZH":"2018060003_ggkz","KZM":"大类基础课","XNXQ":"2020-2021-2","CXXQ":null,"KCM":"高等代数（II）","PX":null,"KCH":"MS202065"},{"PYFADM":"61ff62ed9a3a480eaf7ca0bbbe3e8bd0","XS":"48.0","KCXZDM_DISPLAY":"必修","WID":"5ec4f516f7184e0f9bcc8b389e874324","XNXQ_DISPLAY":"2020-2021学年第一学期","KKDWDM_DISPLAY":"数学与统计学院","BZ":null,"XXKC":null,"SFZGKC":null,"XF":"3.0","JHXNDM":null,"KSLXDM_DISPLAY":"考试","KCXZDM":"001","XDXQ":"1","SFZGKC_DISPLAY":"","XDXNXQ":null,"KKDWDM":"1107","KSLXDM":"1","JHXQDM":null,"KZH":"2018060003_ggkz","KZM":"大类基础课","XNXQ":"2020-2021-1","CXXQ":null,"KCM":"空间解析几何","PX":null,"KCH":"MS202066"},{"PYFADM":"61ff62ed9a3a480eaf7ca0bbbe3e8bd0","XS":"48.0","KCXZDM_DISPLAY":"必修","WID":"C1CCC44EC91505B0E0530D13AC0A4A70","XNXQ_DISPLAY":"2021-2022学年第二学期","KKDWDM_DISPLAY":"数学与统计学院","BZ":null,"XXKC":null,"SFZGKC":"0","XF":"3.0","JHXNDM":null,"KSLXDM_DISPLAY":"考试","KCXZDM":"001","XDXQ":"4","SFZGKC_DISPLAY":"否","XDXNXQ":null,"KKDWDM":"1107","KSLXDM":"1","JHXQDM":null,"KZH":"9a208ea7dc7c4ae699e040be84dd8db4","KZM":"专业核心课","XNXQ":"2021-2022-2","CXXQ":null,"KCM":"概率论","PX":null,"KCH":"MS204001"},{"PYFADM":"61ff62ed9a3a480eaf7ca0bbbe3e8bd0","XS":"52.0","KCXZDM_DISPLAY":"必修","WID":"C1CCC44EC91605B0E0530D13AC0A4A70","XNXQ_DISPLAY":"2021-2022学年第二学期","KKDWDM_DISPLAY":"数学与统计学院","BZ":null,"XXKC":null,"SFZGKC":"0","XF":"3.0","JHXNDM":null,"KSLXDM_DISPLAY":"考试","KCXZDM":"001","XDXQ":"4","SFZGKC_DISPLAY":"否","XDXNXQ":null,"KKDWDM":"1107","KSLXDM":"1","JHXQDM":null,"KZH":"9a208ea7dc7c4ae699e040be84dd8db4","KZM":"专业核心课","XNXQ":"2021-2022-2","CXXQ":null,"KCM":"运筹与最优化方法","PX":null,"KCH":"MS204003"},{"PYFADM":"61ff62ed9a3a480eaf7ca0bbbe3e8bd0","XS":"48.0","KCXZDM_DISPLAY":"必修","WID":"C1CCC44EC94C05B0E0530D13AC0A4A70","XNXQ_DISPLAY":"2022-2023学年第一学期","KKDWDM_DISPLAY":"数学与统计学院","BZ":null,"XXKC":null,"SFZGKC":null,"XF":"3.0","JHXNDM":null,"KSLXDM_DISPLAY":"考试","KCXZDM":"001","XDXQ":"5","SFZGKC_DISPLAY":"","XDXNXQ":null,"KKDWDM":"1107","KSLXDM":"1","JHXQDM":null,"KZH":"9a208ea7dc7c4ae699e040be84dd8db4","KZM":"专业核心课","XNXQ":"2022-2023-1","CXXQ":null,"KCM":"数值分析","PX":null,"KCH":"MS204004"},{"PYFADM":"61ff62ed9a3a480eaf7ca0bbbe3e8bd0","XS":"48.0","KCXZDM_DISPLAY":"学院限选","WID":"C1CCC44EC94D05B0E0530D13AC0A4A70","XNXQ_DISPLAY":"2022-2023学年第一学期","KKDWDM_DISPLAY":"数学与统计学院","BZ":null,"XXKC":null,"SFZGKC":null,"XF":"3.0","JHXNDM":null,"KSLXDM_DISPLAY":"考试","KCXZDM":"013","XDXQ":"5","SFZGKC_DISPLAY":"","XDXNXQ":null,"KKDWDM":"1107","KSLXDM":"1","JHXQDM":null,"KZH":"60643a2a671f4a5e8dc5306f698e3753","KZM":"专业选修课","XNXQ":"2022-2023-1","CXXQ":null,"KCM":"随机过程","PX":null,"KCH":"MS204005"},{"PYFADM":"61ff62ed9a3a480eaf7ca0bbbe3e8bd0","XS":"48.0","KCXZDM_DISPLAY":"必修","WID":"C1CCC44EC91705B0E0530D13AC0A4A70","XNXQ_DISPLAY":"2021-2022学年第一学期","KKDWDM_DISPLAY":"数学与统计学院","BZ":null,"XXKC":null,"SFZGKC":"0","XF":"3.0","JHXNDM":null,"KSLXDM_DISPLAY":"考试","KCXZDM":"001","XDXQ":"3","SFZGKC_DISPLAY":"否","XDXNXQ":null,"KKDWDM":"1107","KSLXDM":"1","JHXQDM":null,"KZH":"9a208ea7dc7c4ae699e040be84dd8db4","KZM":"专业核心课","XNXQ":"2021-2022-1","CXXQ":null,"KCM":"近世代数","PX":null,"KCH":"MS204006"},{"PYFADM":"61ff62ed9a3a480eaf7ca0bbbe3e8bd0","XS":"48.0","KCXZDM_DISPLAY":"学院任选","WID":"C1CCC44EC90C05B0E0530D13AC0A4A70","XNXQ_DISPLAY":"2021-2022学年第二学期","KKDWDM_DISPLAY":"数学与统计学院","BZ":null,"XXKC":null,"SFZGKC":"0","XF":"3.0","JHXNDM":null,"KSLXDM_DISPLAY":"考查","KCXZDM":"014","XDXQ":"4","SFZGKC_DISPLAY":"否","XDXNXQ":null,"KKDWDM":"1107","KSLXDM":"2","JHXQDM":null,"KZH":"60643a2a671f4a5e8dc5306f698e3753","KZM":"专业选修课","XNXQ":"2021-2022-2","CXXQ":null,"KCM":"数据结构","PX":null,"KCH":"MS204007"},{"PYFADM":"61ff62ed9a3a480eaf7ca0bbbe3e8bd0","XS":"48.0","KCXZDM_DISPLAY":"学院限选","WID":"C1CCC44EC90D05B0E0530D13AC0A4A70","XNXQ_DISPLAY":"2021-2022学年第二学期","KKDWDM_DISPLAY":"数学与统计学院","BZ":null,"XXKC":null,"SFZGKC":"0","XF":"3.0","JHXNDM":null,"KSLXDM_DISPLAY":"考试","KCXZDM":"013","XDXQ":"4","SFZGKC_DISPLAY":"否","XDXNXQ":null,"KKDWDM":"1107","KSLXDM":"1","JHXQDM":null,"KZH":"60643a2a671f4a5e8dc5306f698e3753","KZM":"专业选修课","XNXQ":"2021-2022-2","CXXQ":null,"KCM":"数学建模","PX":null,"KCH":"MS204008"},{"PYFADM":"61ff62ed9a3a480eaf7ca0bbbe3e8bd0","XS":"48.0","KCXZDM_DISPLAY":"学院任选","WID":"C1CCC44EC90E05B0E0530D13AC0A4A70","XNXQ_DISPLAY":"2021-2022学年第二学期","KKDWDM_DISPLAY":"数学与统计学院","BZ":null,"XXKC":null,"SFZGKC":"0","XF":"3.0","JHXNDM":null,"KSLXDM_DISPLAY":"考试","KCXZDM":"014","XDXQ":"4","SFZGKC_DISPLAY":"否","XDXNXQ":null,"KKDWDM":"1107","KSLXDM":"1","JHXQDM":null,"KZH":"60643a2a671f4a5e8dc5306f698e3753","KZM":"专业选修课","XNXQ":"2021-2022-2","CXXQ":null,"KCM":"数学软件与实验","PX":null,"KCH":"MS204009"},{"PYFADM":"61ff62ed9a3a480eaf7ca0bbbe3e8bd0","XS":"48.0","KCXZDM_DISPLAY":"必修","WID":"C1CCC44EC94E05B0E0530D13AC0A4A70","XNXQ_DISPLAY":"2022-2023学年第一学期","KKDWDM_DISPLAY":"数学与统计学院","BZ":null,"XXKC":null,"SFZGKC":null,"XF":"3.0","JHXNDM":null,"KSLXDM_DISPLAY":"考试","KCXZDM":"001","XDXQ":"5","SFZGKC_DISPLAY":"","XDXNXQ":null,"KKDWDM":"1107","KSLXDM":"1","JHXQDM":null,"KZH":"9a208ea7dc7c4ae699e040be84dd8db4","KZM":"专业核心课","XNXQ":"2022-2023-1","CXXQ":null,"KCM":"泛函分析","PX":null,"KCH":"MS204010"},{"PYFADM":"61ff62ed9a3a480eaf7ca0bbbe3e8bd0","XS":"48.0","KCXZDM_DISPLAY":"学院任选","WID":"C1CCC44EC94F05B0E0530D13AC0A4A70","XNXQ_DISPLAY":"2022-2023学年第一学期","KKDWDM_DISPLAY":"数学与统计学院","BZ":null,"XXKC":null,"SFZGKC":null,"XF":"3.0","JHXNDM":null,"KSLXDM_DISPLAY":"考试","KCXZDM":"014","XDXQ":"5","SFZGKC_DISPLAY":"","XDXNXQ":null,"KKDWDM":"1107","KSLXDM":"1","JHXQDM":null,"KZH":"60643a2a671f4a5e8dc5306f698e3753","KZM":"专业选修课","XNXQ":"2022-2023-1","CXXQ":null,"KCM":"数学物理方程","PX":null,"KCH":"MS204011"},{"PYFADM":"61ff62ed9a3a480eaf7ca0bbbe3e8bd0","XS":"32.0","KCXZDM_DISPLAY":"学院任选","WID":"C1CCC44EC93A05B0E0530D13AC0A4A70","XNXQ_DISPLAY":"2022-2023学年第二学期","KKDWDM_DISPLAY":"数学与统计学院","BZ":null,"XXKC":null,"SFZGKC":null,"XF":"2.0","JHXNDM":null,"KSLXDM_DISPLAY":"考试","KCXZDM":"014","XDXQ":"6","SFZGKC_DISPLAY":"","XDXNXQ":null,"KKDWDM":"1107","KSLXDM":"1","JHXQDM":null,"KZH":"60643a2a671f4a5e8dc5306f698e3753","KZM":"专业选修课","XNXQ":"2022-2023-2","CXXQ":null,"KCM":"现代数据分析","PX":null,"KCH":"MS204012"},{"PYFADM":"61ff62ed9a3a480eaf7ca0bbbe3e8bd0","XS":"48.0","KCXZDM_DISPLAY":"学院限选","WID":"C1CCC44EC93C05B0E0530D13AC0A4A70","XNXQ_DISPLAY":"2022-2023学年第二学期","KKDWDM_DISPLAY":"数学与统计学院","BZ":null,"XXKC":null,"SFZGKC":null,"XF":"3.0","JHXNDM":null,"KSLXDM_DISPLAY":"考试","KCXZDM":"013","XDXQ":"6","SFZGKC_DISPLAY":"","XDXNXQ":null,"KKDWDM":"1107","KSLXDM":"1","JHXQDM":null,"KZH":"60643a2a671f4a5e8dc5306f698e3753","KZM":"专业选修课","XNXQ":"2022-2023-2","CXXQ":null,"KCM":"分析与代数续论","PX":null,"KCH":"MS204014"},{"PYFADM":"61ff62ed9a3a480eaf7ca0bbbe3e8bd0","XS":"32.0","KCXZDM_DISPLAY":"学院任选","WID":"C1CCC44EC90F05B0E0530D13AC0A4A70","XNXQ_DISPLAY":"2021-2022学年第二学期","KKDWDM_DISPLAY":"数学与统计学院","BZ":null,"XXKC":null,"SFZGKC":"0","XF":"2.0","JHXNDM":null,"KSLXDM_DISPLAY":"考试","KCXZDM":"014","XDXQ":"4","SFZGKC_DISPLAY":"否","XDXNXQ":null,"KKDWDM":"1107","KSLXDM":"1","JHXQDM":null,"KZH":"60643a2a671f4a5e8dc5306f698e3753","KZM":"专业选修课","XNXQ":"2021-2022-2","CXXQ":null,"KCM":"拓扑学","PX":null,"KCH":"MS204015"},{"PYFADM":"61ff62ed9a3a480eaf7ca0bbbe3e8bd0","XS":"48.0","KCXZDM_DISPLAY":"学院任选","WID":"C1CCC44EC95005B0E0530D13AC0A4A70","XNXQ_DISPLAY":"2022-2023学年第一学期","KKDWDM_DISPLAY":"数学与统计学院","BZ":null,"XXKC":null,"SFZGKC":null,"XF":"3.0","JHXNDM":null,"KSLXDM_DISPLAY":"考试","KCXZDM":"014","XDXQ":"5","SFZGKC_DISPLAY":"","XDXNXQ":null,"KKDWDM":"1107","KSLXDM":"1","JHXQDM":null,"KZH":"60643a2a671f4a5e8dc5306f698e3753","KZM":"专业选修课","XNXQ":"2022-2023-1","CXXQ":null,"KCM":"数理统计","PX":null,"KCH":"MS204016"},{"PYFADM":"61ff62ed9a3a480eaf7ca0bbbe3e8bd0","XS":"32.0","KCXZDM_DISPLAY":"学院任选","WID":"C1CCC44EC93E05B0E0530D13AC0A4A70","XNXQ_DISPLAY":"2022-2023学年第二学期","KKDWDM_DISPLAY":"数学与统计学院","BZ":null,"XXKC":null,"SFZGKC":null,"XF":"2.0","JHXNDM":null,"KSLXDM_DISPLAY":"考查","KCXZDM":"014","XDXQ":"6","SFZGKC_DISPLAY":"","XDXNXQ":null,"KKDWDM":"1107","KSLXDM":"2","JHXQDM":null,"KZH":"60643a2a671f4a5e8dc5306f698e3753","KZM":"专业选修课","XNXQ":"2022-2023-2","CXXQ":null,"KCM":"信息论基础","PX":null,"KCH":"MS204018"},{"PYFADM":"61ff62ed9a3a480eaf7ca0bbbe3e8bd0","XS":"32.0","KCXZDM_DISPLAY":"学院任选","WID":"C1CCC44EC94005B0E0530D13AC0A4A70","XNXQ_DISPLAY":"2023-2024-1","KKDWDM_DISPLAY":"数学与统计学院","BZ":null,"XXKC":null,"SFZGKC":null,"XF":"2.0","JHXNDM":null,"KSLXDM_DISPLAY":"考查","KCXZDM":"014","XDXQ":"7","SFZGKC_DISPLAY":"","XDXNXQ":null,"KKDWDM":"1107","KSLXDM":"2","JHXQDM":null,"KZH":"60643a2a671f4a5e8dc5306f698e3753","KZM":"专业选修课","XNXQ":"2023-2024-1","CXXQ":null,"KCM":"计算机网络基础","PX":null,"KCH":"MS204020"},{"PYFADM":"61ff62ed9a3a480eaf7ca0bbbe3e8bd0","XS":"32.0","KCXZDM_DISPLAY":"学院限选","WID":"d522e2b0951f4f3197ccdf59be0dc679","XNXQ_DISPLAY":"2022-2023学年第二学期","KKDWDM_DISPLAY":"数学与统计学院","BZ":null,"XXKC":null,"SFZGKC":null,"XF":"2.0","JHXNDM":null,"KSLXDM_DISPLAY":"考查","KCXZDM":"013","XDXQ":"6","SFZGKC_DISPLAY":"","XDXNXQ":null,"KKDWDM":"1107","KSLXDM":"2","JHXQDM":null,"KZH":"60643a2a671f4a5e8dc5306f698e3753","KZM":"专业选修课","XNXQ":"2022-2023-2","CXXQ":null,"KCM":"智能控制","PX":null,"KCH":"MS204021"},{"PYFADM":"61ff62ed9a3a480eaf7ca0bbbe3e8bd0","XS":"32.0","KCXZDM_DISPLAY":"学院任选","WID":"C1CCC44EC94105B0E0530D13AC0A4A70","XNXQ_DISPLAY":"2023-2024-1","KKDWDM_DISPLAY":"数学与统计学院","BZ":null,"XXKC":null,"SFZGKC":null,"XF":"2.0","JHXNDM":null,"KSLXDM_DISPLAY":"考查","KCXZDM":"014","XDXQ":"7","SFZGKC_DISPLAY":"","XDXNXQ":null,"KKDWDM":"1107","KSLXDM":"2","JHXQDM":null,"KZH":"60643a2a671f4a5e8dc5306f698e3753","KZM":"专业选修课","XNXQ":"2023-2024-1","CXXQ":null,"KCM":"数学与统计前沿研究选讲","PX":null,"KCH":"MS204022"},{"PYFADM":"61ff62ed9a3a480eaf7ca0bbbe3e8bd0","XS":"32.0","KCXZDM_DISPLAY":"学院任选","WID":"C1CCC44EC94205B0E0530D13AC0A4A70","XNXQ_DISPLAY":"2022-2023学年第二学期","KKDWDM_DISPLAY":"数学与统计学院","BZ":null,"XXKC":null,"SFZGKC":null,"XF":"2.0","JHXNDM":null,"KSLXDM_DISPLAY":"考查","KCXZDM":"014","XDXQ":"6","SFZGKC_DISPLAY":"","XDXNXQ":null,"KKDWDM":"1107","KSLXDM":"2","JHXQDM":null,"KZH":"60643a2a671f4a5e8dc5306f698e3753","KZM":"专业选修课","XNXQ":"2022-2023-2","CXXQ":null,"KCM":"模糊数学","PX":null,"KCH":"MS204023"},{"PYFADM":"61ff62ed9a3a480eaf7ca0bbbe3e8bd0","XS":"32.0","KCXZDM_DISPLAY":"学院任选","WID":"C1CCC44EC95105B0E0530D13AC0A4A70","XNXQ_DISPLAY":"2022-2023学年第一学期","KKDWDM_DISPLAY":"数学与统计学院","BZ":null,"XXKC":null,"SFZGKC":null,"XF":"2.0","JHXNDM":null,"KSLXDM_DISPLAY":"考查","KCXZDM":"014","XDXQ":"5","SFZGKC_DISPLAY":"","XDXNXQ":null,"KKDWDM":"1107","KSLXDM":"2","JHXQDM":null,"KZH":"60643a2a671f4a5e8dc5306f698e3753","KZM":"专业选修课","XNXQ":"2022-2023-1","CXXQ":null,"KCM":"测度论","PX":null,"KCH":"MS204024"},{"PYFADM":"61ff62ed9a3a480eaf7ca0bbbe3e8bd0","XS":"48.0","KCXZDM_DISPLAY":"必修","WID":"b87de6e3ab2c4f4a8cc786cb26086f5c","XNXQ_DISPLAY":"2022-2023学年第一学期","KKDWDM_DISPLAY":"数学与统计学院","BZ":null,"XXKC":null,"SFZGKC":null,"XF":"3.0","JHXNDM":null,"KSLXDM_DISPLAY":"考试","KCXZDM":"001","XDXQ":"5","SFZGKC_DISPLAY":"","XDXNXQ":null,"KKDWDM":"1107","KSLXDM":"1","JHXQDM":null,"KZH":"9a208ea7dc7c4ae699e040be84dd8db4","KZM":"专业核心课","XNXQ":"2022-2023-1","CXXQ":null,"KCM":"现代控制理论","PX":null,"KCH":"MS204027"},{"PYFADM":"61ff62ed9a3a480eaf7ca0bbbe3e8bd0","XS":"48.0","KCXZDM_DISPLAY":"必修","WID":"a075bbb3a72044fcbb98e2006f0ae929","XNXQ_DISPLAY":"2022-2023学年第二学期","KKDWDM_DISPLAY":"数学与统计学院","BZ":null,"XXKC":null,"SFZGKC":null,"XF":"3.0","JHXNDM":null,"KSLXDM_DISPLAY":"考试","KCXZDM":"001","XDXQ":"6","SFZGKC_DISPLAY":"","XDXNXQ":null,"KKDWDM":"1107","KSLXDM":"1","JHXQDM":null,"KZH":"9a208ea7dc7c4ae699e040be84dd8db4","KZM":"专业核心课","XNXQ":"2022-2023-2","CXXQ":null,"KCM":"数字信号与图像处理","PX":null,"KCH":"MS204043"},{"PYFADM":"61ff62ed9a3a480eaf7ca0bbbe3e8bd0","XS":"48.0","KCXZDM_DISPLAY":"学院任选","WID":"b22bbaf202e74931a820433896b9a748","XNXQ_DISPLAY":"2022-2023学年第二学期","KKDWDM_DISPLAY":"数学与统计学院","BZ":null,"XXKC":null,"SFZGKC":null,"XF":"3.0","JHXNDM":null,"KSLXDM_DISPLAY":"考试","KCXZDM":"014","XDXQ":"6","SFZGKC_DISPLAY":"","XDXNXQ":null,"KKDWDM":"1107","KSLXDM":"1","JHXQDM":null,"KZH":"60643a2a671f4a5e8dc5306f698e3753","KZM":"专业选修课","XNXQ":"2022-2023-2","CXXQ":null,"KCM":"矩阵分析","PX":null,"KCH":"MS204044"},{"PYFADM":"61ff62ed9a3a480eaf7ca0bbbe3e8bd0","XS":"32.0","KCXZDM_DISPLAY":"学院任选","WID":"606a4d0c1fd1447aa36cec108ef2c87c","XNXQ_DISPLAY":"2023-2024-1","KKDWDM_DISPLAY":"数学与统计学院","BZ":null,"XXKC":null,"SFZGKC":null,"XF":"2.0","JHXNDM":null,"KSLXDM_DISPLAY":"考查","KCXZDM":"014","XDXQ":"7","SFZGKC_DISPLAY":"","XDXNXQ":null,"KKDWDM":"1107","KSLXDM":"2","JHXQDM":null,"KZH":"60643a2a671f4a5e8dc5306f698e3753","KZM":"专业选修课","XNXQ":"2023-2024-1","CXXQ":null,"KCM":"小波分析及其应用","PX":null,"KCH":"MS204045"},{"PYFADM":"61ff62ed9a3a480eaf7ca0bbbe3e8bd0","XS":"48.0","KCXZDM_DISPLAY":"必修","WID":"8cf26d34ca354445846d347c45cc78af","XNXQ_DISPLAY":"2022-2023学年第二学期","KKDWDM_DISPLAY":"数学与统计学院","BZ":null,"XXKC":null,"SFZGKC":null,"XF":"3.0","JHXNDM":null,"KSLXDM_DISPLAY":"考试","KCXZDM":"001","XDXQ":"6","SFZGKC_DISPLAY":"","XDXNXQ":null,"KKDWDM":"1107","KSLXDM":"1","JHXQDM":null,"KZH":"9a208ea7dc7c4ae699e040be84dd8db4","KZM":"专业核心课","XNXQ":"2022-2023-2","CXXQ":null,"KCM":"现代密码学","PX":null,"KCH":"MS204061"},{"PYFADM":"61ff62ed9a3a480eaf7ca0bbbe3e8bd0","XS":"32.0","KCXZDM_DISPLAY":"学院任选","WID":"C1CCC44EC94305B0E0530D13AC0A4A70","XNXQ_DISPLAY":"2022-2023学年第二学期","KKDWDM_DISPLAY":"数学与统计学院","BZ":null,"XXKC":null,"SFZGKC":null,"XF":"2.0","JHXNDM":null,"KSLXDM_DISPLAY":"考查","KCXZDM":"014","XDXQ":"6","SFZGKC_DISPLAY":"","XDXNXQ":null,"KKDWDM":"1107","KSLXDM":"2","JHXQDM":null,"KZH":"60643a2a671f4a5e8dc5306f698e3753","KZM":"专业选修课","XNXQ":"2022-2023-2","CXXQ":null,"KCM":"生物数学","PX":null,"KCH":"MS204063"},{"PYFADM":"61ff62ed9a3a480eaf7ca0bbbe3e8bd0","XS":"32.0","KCXZDM_DISPLAY":"学院任选","WID":"C1CCC44EC94405B0E0530D13AC0A4A70","XNXQ_DISPLAY":"2023-2024-1","KKDWDM_DISPLAY":"数学与统计学院","BZ":null,"XXKC":null,"SFZGKC":null,"XF":"2.0","JHXNDM":null,"KSLXDM_DISPLAY":"考查","KCXZDM":"014","XDXQ":"7","SFZGKC_DISPLAY":"","XDXNXQ":null,"KKDWDM":"1107","KSLXDM":"2","JHXQDM":null,"KZH":"60643a2a671f4a5e8dc5306f698e3753","KZM":"专业选修课","XNXQ":"2023-2024-1","CXXQ":null,"KCM":"算子代数","PX":null,"KCH":"MS204064"},{"PYFADM":"61ff62ed9a3a480eaf7ca0bbbe3e8bd0","XS":"16.0","KCXZDM_DISPLAY":"必修","WID":"C1CCC44EC94505B0E0530D13AC0A4A70","XNXQ_DISPLAY":"2023-2024-1, 2023-2024-2","KKDWDM_DISPLAY":"数学与统计学院","BZ":null,"XXKC":null,"SFZGKC":null,"XF":"16.0","JHXNDM":null,"KSLXDM_DISPLAY":"考查","KCXZDM":"001","XDXQ":"7,8","SFZGKC_DISPLAY":"","XDXNXQ":null,"KKDWDM":"1107","KSLXDM":"2","JHXQDM":null,"KZH":"782b37c5df7d49ca8bb41b589719948c","KZM":"集中实践环节","XNXQ":"2023-2024-1,2023-2024-2","CXXQ":null,"KCM":"毕业设计","PX":null,"KCH":"MS207001"},{"PYFADM":"61ff62ed9a3a480eaf7ca0bbbe3e8bd0","XS":"58.0","KCXZDM_DISPLAY":"必修","WID":"C1CCC44EC92205B0E0530D13AC0A4A70","XNXQ_DISPLAY":"2020-2021学年第二学期","KKDWDM_DISPLAY":"物理与光电工程学院","BZ":null,"XXKC":null,"SFZGKC":"0","XF":"3.5","JHXNDM":null,"KSLXDM_DISPLAY":"考试","KCXZDM":"001","XDXQ":"2","SFZGKC_DISPLAY":"否","XDXNXQ":null,"KKDWDM":"1105","KSLXDM":"1","JHXQDM":null,"KZH":"3a0401dbd12547e38997f59d2ad4110c","KZM":"通识教育基础课","XNXQ":"2020-2021-2","CXXQ":null,"KCM":"大学物理(Ⅰ)","PX":null,"KCH":"PY006001"},{"PYFADM":"61ff62ed9a3a480eaf7ca0bbbe3e8bd0","XS":"54.0","KCXZDM_DISPLAY":"必修","WID":"C1CCC44EC91305B0E0530D13AC0A4A70","XNXQ_DISPLAY":"2021-2022学年第一学期","KKDWDM_DISPLAY":"物理学院","BZ":null,"XXKC":null,"SFZGKC":"0","XF":"3.5","JHXNDM":null,"KSLXDM_DISPLAY":"考试","KCXZDM":"001","XDXQ":"3","SFZGKC_DISPLAY":"否","XDXNXQ":null,"KKDWDM":"528","KSLXDM":"1","JHXQDM":null,"KZH":"3a0401dbd12547e38997f59d2ad4110c","KZM":"通识教育基础课","XNXQ":"2021-2022-1","CXXQ":null,"KCM":"大学物理(II)","PX":null,"KCH":"PY006002"},{"PYFADM":"61ff62ed9a3a480eaf7ca0bbbe3e8bd0","XS":"13.5","KCXZDM_DISPLAY":"必修","WID":"C1CCC44EC92305B0E0530D13AC0A4A70","XNXQ_DISPLAY":"2020-2021学年第二学期","KKDWDM_DISPLAY":"物理与光电工程学院","BZ":null,"XXKC":null,"SFZGKC":"0","XF":"1.0","JHXNDM":null,"KSLXDM_DISPLAY":"考查","KCXZDM":"001","XDXQ":"2","SFZGKC_DISPLAY":"否","XDXNXQ":null,"KKDWDM":"1105","KSLXDM":"2","JHXQDM":null,"KZH":"3a0401dbd12547e38997f59d2ad4110c","KZM":"通识教育基础课","XNXQ":"2020-2021-2","CXXQ":null,"KCM":"物理实验(Ⅰ)","PX":null,"KCH":"PY006003"},{"PYFADM":"61ff62ed9a3a480eaf7ca0bbbe3e8bd0","XS":"13.5","KCXZDM_DISPLAY":"必修","WID":"C1CCC44EC91405B0E0530D13AC0A4A70","XNXQ_DISPLAY":"2021-2022学年第一学期","KKDWDM_DISPLAY":"物理学院","BZ":null,"XXKC":null,"SFZGKC":"0","XF":"1.0","JHXNDM":null,"KSLXDM_DISPLAY":"考查","KCXZDM":"001","XDXQ":"3","SFZGKC_DISPLAY":"否","XDXNXQ":null,"KKDWDM":"528","KSLXDM":"2","JHXQDM":null,"KZH":"3a0401dbd12547e38997f59d2ad4110c","KZM":"通识教育基础课","XNXQ":"2021-2022-1","CXXQ":null,"KCM":"物理实验(II)","PX":null,"KCH":"PY006004"},{"PYFADM":"61ff62ed9a3a480eaf7ca0bbbe3e8bd0","XS":"16.0","KCXZDM_DISPLAY":"必修","WID":"C1CCC44EC91905B0E0530D13AC0A4A70","XNXQ_DISPLAY":"2020-2021学年第一学期","KKDWDM_DISPLAY":"数学与统计学院","BZ":null,"XXKC":null,"SFZGKC":"0","XF":"1.0","JHXNDM":null,"KSLXDM_DISPLAY":"考查","KCXZDM":"001","XDXQ":"1","SFZGKC_DISPLAY":"否","XDXNXQ":null,"KKDWDM":"1107","KSLXDM":"2","JHXQDM":null,"KZH":"3a0401dbd12547e38997f59d2ad4110c","KZM":"通识教育基础课","XNXQ":"2020-2021-1","CXXQ":null,"KCM":"新生研讨课","PX":null,"KCH":"TS006007"},{"PYFADM":"61ff62ed9a3a480eaf7ca0bbbe3e8bd0","XS":"16.0","KCXZDM_DISPLAY":"必修","WID":"C1CCC44EC93705B0E0530D13AC0A4A70","XNXQ_DISPLAY":"2020-2021学年第一学期","KKDWDM_DISPLAY":"本科生院","BZ":null,"XXKC":null,"SFZGKC":"0","XF":"1.0","JHXNDM":null,"KSLXDM_DISPLAY":"考查","KCXZDM":"001","XDXQ":"1","SFZGKC_DISPLAY":"否","XDXNXQ":null,"KKDWDM":"0001","KSLXDM":"2","JHXQDM":null,"KZH":"b6d9c5a875e9420bb4f3743ae648f7c9","KZM":"新生网上前置教育","XNXQ":"2020-2021-1","CXXQ":null,"KCM":"新生网上前置教育","PX":null,"KCH":"TS006010"},{"PYFADM":"61ff62ed9a3a480eaf7ca0bbbe3e8bd0","XS":"16.0","KCXZDM_DISPLAY":"必修","WID":"D57C8321A3E86A7CE0530D13AC0ADBDC","XNXQ_DISPLAY":"2021-2022学年第一学期","KKDWDM_DISPLAY":"人文学院","BZ":null,"XXKC":null,"SFZGKC":"0","XF":"1.0","JHXNDM":null,"KSLXDM_DISPLAY":"考查","KCXZDM":"001","XDXQ":"3","SFZGKC_DISPLAY":"否","XDXNXQ":null,"KKDWDM":"1108","KSLXDM":"2","JHXQDM":null,"KZH":"0f1b4df14f8b4beb83962542aa074756","KZM":"2021试点班-素质能力拓展","XNXQ":"2021-2022-1","CXXQ":null,"KCM":"写作与沟通","PX":null,"KCH":"TS006011"},{"PYFADM":"61ff62ed9a3a480eaf7ca0bbbe3e8bd0","XS":"8.0","KCXZDM_DISPLAY":"必修","WID":"D57C8321A3E66A7CE0530D13AC0ADBDC","XNXQ_DISPLAY":"2021-2022学年第二学期, 2022-2023学年第一学期, 2022-2023学年第二学期, 2023-2024-1, 2023-2024-2","KKDWDM_DISPLAY":"本科生院","BZ":null,"XXKC":null,"SFZGKC":null,"XF":"0.5","JHXNDM":null,"KSLXDM_DISPLAY":"考查","KCXZDM":"001","XDXQ":"4,5,6,7,8","SFZGKC_DISPLAY":"","XDXNXQ":null,"KKDWDM":"0001","KSLXDM":"2","JHXQDM":null,"KZH":"0f1b4df14f8b4beb83962542aa074756","KZM":"2021试点班-素质能力拓展","XNXQ":"2021-2022-2,2022-2023-1,2022-2023-2,2023-2024-1,2023-2024-2","CXXQ":null,"KCM":"“红色筑梦”实践基础I","PX":null,"KCH":"TS006013"},{"PYFADM":"61ff62ed9a3a480eaf7ca0bbbe3e8bd0","XS":"16.0","KCXZDM_DISPLAY":"必修","WID":"D57C8321A3E56A7CE0530D13AC0ADBDC","XNXQ_DISPLAY":"2022-2023学年第一学期, 2022-2023学年第二学期, 2023-2024-1, 2023-2024-2","KKDWDM_DISPLAY":"本科生院","BZ":null,"XXKC":null,"SFZGKC":"0","XF":"1.0","JHXNDM":null,"KSLXDM_DISPLAY":"考查","KCXZDM":"001","XDXQ":"5,6,7,8","SFZGKC_DISPLAY":"否","XDXNXQ":null,"KKDWDM":"0001","KSLXDM":"2","JHXQDM":null,"KZH":"0f1b4df14f8b4beb83962542aa074756","KZM":"2021试点班-素质能力拓展","XNXQ":"2022-2023-1,2022-2023-2,2023-2024-1,2023-2024-2","CXXQ":null,"KCM":"“红色筑梦”实践基础II","PX":null,"KCH":"TS006019"},{"PYFADM":"61ff62ed9a3a480eaf7ca0bbbe3e8bd0","XS":"16.0","KCXZDM_DISPLAY":"必修","WID":"D57C8321A3E76A7CE0530D13AC0ADBDC","XNXQ_DISPLAY":"2020-2021学年第一学期, 2020-2021学年第二学期, 2021-2022学年第一学期, 2021-2022学年第二学期, 2022-2023学年第一学期, 2022-2023学年第二学期, 2023-2024-1, 2023-2024-2","KKDWDM_DISPLAY":"本科生院","BZ":null,"XXKC":null,"SFZGKC":null,"XF":"1.0","JHXNDM":null,"KSLXDM_DISPLAY":"考查","KCXZDM":"001","XDXQ":"1,2,3,4,5,6,7,8","SFZGKC_DISPLAY":"","XDXNXQ":null,"KKDWDM":"0001","KSLXDM":"2","JHXQDM":null,"KZH":"0f1b4df14f8b4beb83962542aa074756","KZM":"2021试点班-素质能力拓展","XNXQ":"2020-2021-1,2020-2021-2,2021-2022-1,2021-2022-2,2022-2023-1,2022-2023-2,2023-2024-1,2023-2024-2","CXXQ":null,"KCM":"大学生职业发展","PX":null,"KCH":"TS006025"},{"PYFADM":"61ff62ed9a3a480eaf7ca0bbbe3e8bd0","XS":"24.0","KCXZDM_DISPLAY":"必修","WID":"C1CCC44EC8FE05B0E0530D13AC0A4A70","XNXQ_DISPLAY":"2022-2023学年第二学期","KKDWDM_DISPLAY":"数学与统计学院","BZ":null,"XXKC":null,"SFZGKC":null,"XF":"1.5","JHXNDM":null,"KSLXDM_DISPLAY":"考查","KCXZDM":"001","XDXQ":"6","SFZGKC_DISPLAY":"","XDXNXQ":null,"KKDWDM":"1107","KSLXDM":"2","JHXQDM":null,"KZH":"37dbb78bdf4a422b8d86d0e3aab7911c","KZM":"就业指导","XNXQ":"2022-2023-2","CXXQ":null,"KCM":"就业指导","PX":null,"KCH":"TS006026-07"},{"PYFADM":"61ff62ed9a3a480eaf7ca0bbbe3e8bd0","XS":"16.0","KCXZDM_DISPLAY":"必修","WID":"D57C8321A3EB6A7CE0530D13AC0ADBDC","XNXQ_DISPLAY":"2020-2021学年第一学期, 2020-2021学年第二学期, 2021-2022学年第一学期, 2021-2022学年第二学期, 2022-2023学年第一学期, 2022-2023学年第二学期","KKDWDM_DISPLAY":"本科生院","BZ":null,"XXKC":null,"SFZGKC":"0","XF":"1.0","JHXNDM":null,"KSLXDM_DISPLAY":"考查","KCXZDM":"001","XDXQ":"1,2,3,4,5,6","SFZGKC_DISPLAY":"否","XDXNXQ":null,"KKDWDM":"0001","KSLXDM":"2","JHXQDM":null,"KZH":"0f1b4df14f8b4beb83962542aa074756","KZM":"2021试点班-素质能力拓展","XNXQ":"2020-2021-1,2020-2021-2,2021-2022-1,2021-2022-2,2022-2023-1,2022-2023-2","CXXQ":null,"KCM":"劳动教育实践","PX":null,"KCH":"TS006028"},{"PYFADM":"61ff62ed9a3a480eaf7ca0bbbe3e8bd0","XS":"16.0","KCXZDM_DISPLAY":"必修","WID":"D57C8321A3EA6A7CE0530D13AC0ADBDC","XNXQ_DISPLAY":"2020-2021学年第一学期, 2020-2021学年第二学期, 2021-2022学年第一学期, 2021-2022学年第二学期, 2022-2023学年第一学期, 2022-2023学年第二学期, 2023-2024-1, 2023-2024-2","KKDWDM_DISPLAY":"本科生院","BZ":null,"XXKC":null,"SFZGKC":"0","XF":"1.0","JHXNDM":null,"KSLXDM_DISPLAY":"考查","KCXZDM":"001","XDXQ":"1,2,3,4,5,6,7,8","SFZGKC_DISPLAY":"否","XDXNXQ":null,"KKDWDM":"0001","KSLXDM":"2","JHXQDM":null,"KZH":"0f1b4df14f8b4beb83962542aa074756","KZM":"2021试点班-素质能力拓展","XNXQ":"2020-2021-1,2020-2021-2,2021-2022-1,2021-2022-2,2022-2023-1,2022-2023-2,2023-2024-1,2023-2024-2","CXXQ":null,"KCM":"劳动教育","PX":null,"KCH":"TS006029"}],"extParams":{"logId":"52d665775db44269915031702129d790","code":1,"totalPage":0}}},"code":"0"}